<?xml version='1.0' encoding='UTF-8'?>
<DEFECTS><DEFECT><SFA><FILEPATH>n:\wpi\cs 502 os\z502 ws\</FILEPATH><FILENAME>z502.c</FILENAME><LINE>347</LINE><COLUMN>14</COLUMN></SFA><DEFECTCODE>6385</DEFECTCODE><DESCRIPTION>Reading invalid data from 'MEMORY':  the readable size is '1024' bytes, but '32767' bytes may be read.</DESCRIPTION><FUNCTION>MemoryCommon</FUNCTION><DECORATED>MemoryCommon</DECORATED><FUNCLINE>231</FUNCLINE><PROBABILITY>1</PROBABILITY><RANK>4</RANK><CATEGORY><RULECATEGORY>mspft</RULECATEGORY></CATEGORY><PATH><SFA><FILEPATH>n:\wpi\cs 502 os\z502 ws\</FILEPATH><FILENAME>z502.c</FILENAME><LINE>232</LINE><COLUMN>7</COLUMN></SFA><SFA><FILEPATH>n:\wpi\cs 502 os\z502 ws\</FILEPATH><FILENAME>z502.c</FILENAME><LINE>233</LINE><COLUMN>7</COLUMN></SFA><SFA><FILEPATH>n:\wpi\cs 502 os\z502 ws\</FILEPATH><FILENAME>z502.c</FILENAME><LINE>234</LINE><COLUMN>7</COLUMN></SFA><SFA><FILEPATH>n:\wpi\cs 502 os\z502 ws\</FILEPATH><FILENAME>z502.c</FILENAME><LINE>235</LINE><COLUMN>7</COLUMN></SFA><SFA><FILEPATH>n:\wpi\cs 502 os\z502 ws\</FILEPATH><FILENAME>z502.c</FILENAME><LINE>236</LINE><COLUMN>7</COLUMN></SFA><SFA><FILEPATH>n:\wpi\cs 502 os\z502 ws\</FILEPATH><FILENAME>z502.c</FILENAME><LINE>237</LINE><COLUMN>7</COLUMN></SFA><SFA><FILEPATH>n:\wpi\cs 502 os\z502 ws\</FILEPATH><FILENAME>z502.c</FILENAME><LINE>238</LINE><COLUMN>7</COLUMN></SFA><SFA><FILEPATH>n:\wpi\cs 502 os\z502 ws\</FILEPATH><FILENAME>z502.c</FILENAME><LINE>239</LINE><COLUMN>6</COLUMN></SFA><SFA><FILEPATH>n:\wpi\cs 502 os\z502 ws\</FILEPATH><FILENAME>z502.c</FILENAME><LINE>240</LINE><COLUMN>6</COLUMN></SFA><SFA><FILEPATH>n:\wpi\cs 502 os\z502 ws\</FILEPATH><FILENAME>z502.c</FILENAME><LINE>242</LINE><COLUMN>7</COLUMN></SFA><SFA><FILEPATH>n:\wpi\cs 502 os\z502 ws\</FILEPATH><FILENAME>z502.c</FILENAME><LINE>243</LINE><COLUMN>8</COLUMN></SFA><SFA><FILEPATH>n:\wpi\cs 502 os\z502 ws\</FILEPATH><FILENAME>z502.c</FILENAME><LINE>244</LINE><COLUMN>20</COLUMN><KEYEVENT><ID>1</ID><KIND>branch</KIND><IMPORTANCE>Full</IMPORTANCE><MESSAGE>Skip this branch, (assume 'VirtualAddress&gt;=2146435072' is false)</MESSAGE></KEYEVENT></SFA><SFA><FILEPATH>n:\wpi\cs 502 os\z502 ws\</FILEPATH><FILENAME>z502.c</FILENAME><LINE>250</LINE><COLUMN>19</COLUMN></SFA><SFA><FILEPATH>n:\wpi\cs 502 os\z502 ws\</FILEPATH><FILENAME>z502.c</FILENAME><LINE>252</LINE><COLUMN>13</COLUMN></SFA><SFA><FILEPATH>n:\wpi\cs 502 os\z502 ws\</FILEPATH><FILENAME>z502.c</FILENAME><LINE>254</LINE><COLUMN>15</COLUMN></SFA><SFA><FILEPATH>n:\wpi\cs 502 os\z502 ws\</FILEPATH><FILENAME>z502.c</FILENAME><LINE>258</LINE><COLUMN>22</COLUMN><KEYEVENT><ID>2</ID><KIND>branch</KIND><IMPORTANCE>Full</IMPORTANCE><MESSAGE>Enter this loop, (assume 'page_is_valid==(BOOL)0')</MESSAGE></KEYEVENT></SFA><SFA><FILEPATH>n:\wpi\cs 502 os\z502 ws\</FILEPATH><FILENAME>z502.c</FILENAME><LINE>259</LINE><COLUMN>13</COLUMN></SFA><SFA><FILEPATH>n:\wpi\cs 502 os\z502 ws\</FILEPATH><FILENAME>z502.c</FILENAME><LINE>260</LINE><COLUMN>24</COLUMN><KEYEVENT><ID>3</ID><KIND>branch</KIND><IMPORTANCE>Full</IMPORTANCE><MESSAGE>Skip this branch, (assume 'VirtualPageNumber&gt;=1024' is false)</MESSAGE></KEYEVENT></SFA><SFA><FILEPATH>n:\wpi\cs 502 os\z502 ws\</FILEPATH><FILENAME>z502.c</FILENAME><LINE>262</LINE><COLUMN>24</COLUMN><KEYEVENT><ID>4</ID><KIND>branch</KIND><IMPORTANCE>Full</IMPORTANCE><MESSAGE>Enter this branch, (assume 'VirtualPageNumber&lt;0')</MESSAGE></KEYEVENT></SFA><SFA><FILEPATH>n:\wpi\cs 502 os\z502 ws\</FILEPATH><FILENAME>z502.c</FILENAME><LINE>263</LINE><COLUMN>14</COLUMN></SFA><SFA><FILEPATH>n:\wpi\cs 502 os\z502 ws\</FILEPATH><FILENAME>z502.c</FILENAME><LINE>264</LINE><COLUMN>28</COLUMN><KEYEVENT><ID>5</ID><KIND>branch</KIND><IMPORTANCE>Full</IMPORTANCE><MESSAGE>Skip this branch, (assume '&lt;branch condition&gt;' is false)</MESSAGE></KEYEVENT></SFA><SFA><FILEPATH>n:\wpi\cs 502 os\z502 ws\</FILEPATH><FILENAME>z502.c</FILENAME><LINE>267</LINE><COLUMN>4</COLUMN><KEYEVENT><ID>6</ID><KIND>branch</KIND><IMPORTANCE>Full</IMPORTANCE><MESSAGE>Skip this branch, (assume '&lt;branch condition&gt;' is false)</MESSAGE></KEYEVENT></SFA><SFA><FILEPATH>n:\wpi\cs 502 os\z502 ws\</FILEPATH><FILENAME>z502.c</FILENAME><LINE>271</LINE><COLUMN>15</COLUMN></SFA><SFA><FILEPATH>n:\wpi\cs 502 os\z502 ws\</FILEPATH><FILENAME>z502.c</FILENAME><LINE>272</LINE><COLUMN>17</COLUMN><KEYEVENT><ID>7</ID><KIND>branch</KIND><IMPORTANCE>Full</IMPORTANCE><MESSAGE>Enter this branch, (assume 'invalidity&gt;0')</MESSAGE></KEYEVENT></SFA><SFA><FILEPATH>n:\wpi\cs 502 os\z502 ws\</FILEPATH><FILENAME>z502.c</FILENAME><LINE>274</LINE><COLUMN>5</COLUMN><KEYEVENT><ID>8</ID><KIND>branch</KIND><IMPORTANCE>Full</IMPORTANCE><MESSAGE>Skip this branch, (assume '&lt;branch condition&gt;' is false)</MESSAGE></KEYEVENT></SFA><SFA><FILEPATH>n:\wpi\cs 502 os\z502 ws\</FILEPATH><FILENAME>z502.c</FILENAME><LINE>281</LINE><COLUMN>40</COLUMN></SFA><SFA><FILEPATH>n:\wpi\cs 502 os\z502 ws\</FILEPATH><FILENAME>z502.c</FILENAME><LINE>283</LINE><COLUMN>14</COLUMN></SFA><SFA><FILEPATH>n:\wpi\cs 502 os\z502 ws\</FILEPATH><FILENAME>z502.c</FILENAME><LINE>284</LINE><COLUMN>16</COLUMN></SFA><SFA><FILEPATH>n:\wpi\cs 502 os\z502 ws\</FILEPATH><FILENAME>z502.c</FILENAME><LINE>286</LINE><COLUMN>10</COLUMN></SFA><SFA><FILEPATH>n:\wpi\cs 502 os\z502 ws\</FILEPATH><FILENAME>z502.c</FILENAME><LINE>258</LINE><COLUMN>22</COLUMN><KEYEVENT><ID>9</ID><KIND>branch</KIND><IMPORTANCE>Full</IMPORTANCE><MESSAGE>Enter this loop, (assume 'page_is_valid==(BOOL)0')</MESSAGE></KEYEVENT></SFA><SFA><FILEPATH>n:\wpi\cs 502 os\z502 ws\</FILEPATH><FILENAME>z502.c</FILENAME><LINE>259</LINE><COLUMN>13</COLUMN></SFA><SFA><FILEPATH>n:\wpi\cs 502 os\z502 ws\</FILEPATH><FILENAME>z502.c</FILENAME><LINE>260</LINE><COLUMN>24</COLUMN><KEYEVENT><ID>10</ID><KIND>branch</KIND><IMPORTANCE>Full</IMPORTANCE><MESSAGE>Skip this branch, (assume 'VirtualPageNumber&gt;=1024' is false)</MESSAGE></KEYEVENT></SFA><SFA><FILEPATH>n:\wpi\cs 502 os\z502 ws\</FILEPATH><FILENAME>z502.c</FILENAME><LINE>262</LINE><COLUMN>24</COLUMN><KEYEVENT><ID>11</ID><KIND>branch</KIND><IMPORTANCE>Full</IMPORTANCE><MESSAGE>Enter this branch, (assume 'VirtualPageNumber&lt;0')</MESSAGE></KEYEVENT></SFA><SFA><FILEPATH>n:\wpi\cs 502 os\z502 ws\</FILEPATH><FILENAME>z502.c</FILENAME><LINE>263</LINE><COLUMN>14</COLUMN></SFA><SFA><FILEPATH>n:\wpi\cs 502 os\z502 ws\</FILEPATH><FILENAME>z502.c</FILENAME><LINE>264</LINE><COLUMN>28</COLUMN><KEYEVENT><ID>12</ID><KIND>branch</KIND><IMPORTANCE>Full</IMPORTANCE><MESSAGE>Skip this branch, (assume '&lt;branch condition&gt;' is false)</MESSAGE></KEYEVENT></SFA><SFA><FILEPATH>n:\wpi\cs 502 os\z502 ws\</FILEPATH><FILENAME>z502.c</FILENAME><LINE>267</LINE><COLUMN>4</COLUMN><KEYEVENT><ID>13</ID><KIND>branch</KIND><IMPORTANCE>Full</IMPORTANCE><MESSAGE>Skip this branch, (assume '&lt;branch condition&gt;' is false)</MESSAGE></KEYEVENT></SFA><SFA><FILEPATH>n:\wpi\cs 502 os\z502 ws\</FILEPATH><FILENAME>z502.c</FILENAME><LINE>271</LINE><COLUMN>15</COLUMN></SFA><SFA><FILEPATH>n:\wpi\cs 502 os\z502 ws\</FILEPATH><FILENAME>z502.c</FILENAME><LINE>272</LINE><COLUMN>17</COLUMN><KEYEVENT><ID>14</ID><KIND>branch</KIND><IMPORTANCE>Full</IMPORTANCE><MESSAGE>Enter this branch, (assume 'invalidity&gt;0')</MESSAGE></KEYEVENT></SFA><SFA><FILEPATH>n:\wpi\cs 502 os\z502 ws\</FILEPATH><FILENAME>z502.c</FILENAME><LINE>274</LINE><COLUMN>5</COLUMN><KEYEVENT><ID>15</ID><KIND>branch</KIND><IMPORTANCE>Full</IMPORTANCE><MESSAGE>Skip this branch, (assume '&lt;branch condition&gt;' is false)</MESSAGE></KEYEVENT></SFA><SFA><FILEPATH>n:\wpi\cs 502 os\z502 ws\</FILEPATH><FILENAME>z502.c</FILENAME><LINE>281</LINE><COLUMN>40</COLUMN></SFA><SFA><FILEPATH>n:\wpi\cs 502 os\z502 ws\</FILEPATH><FILENAME>z502.c</FILENAME><LINE>283</LINE><COLUMN>14</COLUMN></SFA><SFA><FILEPATH>n:\wpi\cs 502 os\z502 ws\</FILEPATH><FILENAME>z502.c</FILENAME><LINE>284</LINE><COLUMN>16</COLUMN></SFA><SFA><FILEPATH>n:\wpi\cs 502 os\z502 ws\</FILEPATH><FILENAME>z502.c</FILENAME><LINE>286</LINE><COLUMN>10</COLUMN></SFA><SFA><FILEPATH>n:\wpi\cs 502 os\z502 ws\</FILEPATH><FILENAME>z502.c</FILENAME><LINE>258</LINE><COLUMN>22</COLUMN><KEYEVENT><ID>16</ID><KIND>branch</KIND><IMPORTANCE>Full</IMPORTANCE><MESSAGE>Continue this loop, (assume 'page_is_valid==(BOOL)0')</MESSAGE></KEYEVENT></SFA><SFA><FILEPATH>n:\wpi\cs 502 os\z502 ws\</FILEPATH><FILENAME>z502.c</FILENAME><LINE>291</LINE><COLUMN>9</COLUMN></SFA><SFA><FILEPATH>n:\wpi\cs 502 os\z502 ws\</FILEPATH><FILENAME>z502.c</FILENAME><LINE>292</LINE><COLUMN>20</COLUMN></SFA><SFA><FILEPATH>n:\wpi\cs 502 os\z502 ws\</FILEPATH><FILENAME>z502.c</FILENAME><LINE>293</LINE><COLUMN>20</COLUMN></SFA><SFA><FILEPATH>n:\wpi\cs 502 os\z502 ws\</FILEPATH><FILENAME>z502.c</FILENAME><LINE>294</LINE><COLUMN>20</COLUMN></SFA><SFA><FILEPATH>n:\wpi\cs 502 os\z502 ws\</FILEPATH><FILENAME>z502.c</FILENAME><LINE>295</LINE><COLUMN>20</COLUMN></SFA><SFA><FILEPATH>n:\wpi\cs 502 os\z502 ws\</FILEPATH><FILENAME>z502.c</FILENAME><LINE>297</LINE><COLUMN>15</COLUMN></SFA><SFA><FILEPATH>n:\wpi\cs 502 os\z502 ws\</FILEPATH><FILENAME>z502.c</FILENAME><LINE>298</LINE><COLUMN>17</COLUMN><KEYEVENT><ID>17</ID><KIND>branch</KIND><IMPORTANCE>Full</IMPORTANCE><MESSAGE>Skip this branch, (assume 'page_offset&gt;(short)16-4' is false)</MESSAGE></KEYEVENT></SFA><SFA><FILEPATH>n:\wpi\cs 502 os\z502 ws\</FILEPATH><FILENAME>z502.c</FILENAME><LINE>331</LINE><COLUMN>17</COLUMN></SFA><SFA><FILEPATH>n:\wpi\cs 502 os\z502 ws\</FILEPATH><FILENAME>z502.c</FILENAME><LINE>338</LINE><COLUMN>3</COLUMN></SFA><SFA><FILEPATH>n:\wpi\cs 502 os\z502 ws\</FILEPATH><FILENAME>z502.c</FILENAME><LINE>344</LINE><COLUMN>38</COLUMN></SFA><SFA><FILEPATH>n:\wpi\cs 502 os\z502 ws\</FILEPATH><FILENAME>z502.c</FILENAME><LINE>346</LINE><COLUMN>19</COLUMN><KEYEVENT><ID>18</ID><KIND>branch</KIND><IMPORTANCE>Full</IMPORTANCE><MESSAGE>Enter this branch, (assume 'read_or_write==0')</MESSAGE></KEYEVENT></SFA><SFA><FILEPATH>n:\wpi\cs 502 os\z502 ws\</FILEPATH><FILENAME>z502.c</FILENAME><LINE>347</LINE><COLUMN>14</COLUMN><KEYEVENT><ID>19</ID><KIND>usage</KIND><IMPORTANCE>Essential</IMPORTANCE><MESSAGE>Invalid read from 'MEMORY[32766]', (readable range is 0 to 1023)</MESSAGE></KEYEVENT></SFA></PATH></DEFECT><DEFECT><SFA><FILEPATH>n:\wpi\cs 502 os\z502 ws\</FILEPATH><FILENAME>z502.c</FILENAME><LINE>355</LINE><COLUMN>29</COLUMN></SFA><DEFECTCODE>6386</DEFECTCODE><DESCRIPTION>Buffer overrun while writing to 'MEMORY':  the writable size is '1024' bytes, but '32767' bytes might be written.</DESCRIPTION><FUNCTION>MemoryCommon</FUNCTION><DECORATED>MemoryCommon</DECORATED><FUNCLINE>231</FUNCLINE><PROBABILITY>1</PROBABILITY><RANK>4</RANK><CATEGORY><RULECATEGORY>mspft</RULECATEGORY></CATEGORY><PATH><SFA><FILEPATH>n:\wpi\cs 502 os\z502 ws\</FILEPATH><FILENAME>z502.c</FILENAME><LINE>232</LINE><COLUMN>7</COLUMN></SFA><SFA><FILEPATH>n:\wpi\cs 502 os\z502 ws\</FILEPATH><FILENAME>z502.c</FILENAME><LINE>233</LINE><COLUMN>7</COLUMN></SFA><SFA><FILEPATH>n:\wpi\cs 502 os\z502 ws\</FILEPATH><FILENAME>z502.c</FILENAME><LINE>234</LINE><COLUMN>7</COLUMN></SFA><SFA><FILEPATH>n:\wpi\cs 502 os\z502 ws\</FILEPATH><FILENAME>z502.c</FILENAME><LINE>235</LINE><COLUMN>7</COLUMN></SFA><SFA><FILEPATH>n:\wpi\cs 502 os\z502 ws\</FILEPATH><FILENAME>z502.c</FILENAME><LINE>236</LINE><COLUMN>7</COLUMN></SFA><SFA><FILEPATH>n:\wpi\cs 502 os\z502 ws\</FILEPATH><FILENAME>z502.c</FILENAME><LINE>237</LINE><COLUMN>7</COLUMN></SFA><SFA><FILEPATH>n:\wpi\cs 502 os\z502 ws\</FILEPATH><FILENAME>z502.c</FILENAME><LINE>238</LINE><COLUMN>7</COLUMN></SFA><SFA><FILEPATH>n:\wpi\cs 502 os\z502 ws\</FILEPATH><FILENAME>z502.c</FILENAME><LINE>239</LINE><COLUMN>6</COLUMN></SFA><SFA><FILEPATH>n:\wpi\cs 502 os\z502 ws\</FILEPATH><FILENAME>z502.c</FILENAME><LINE>240</LINE><COLUMN>6</COLUMN></SFA><SFA><FILEPATH>n:\wpi\cs 502 os\z502 ws\</FILEPATH><FILENAME>z502.c</FILENAME><LINE>242</LINE><COLUMN>7</COLUMN></SFA><SFA><FILEPATH>n:\wpi\cs 502 os\z502 ws\</FILEPATH><FILENAME>z502.c</FILENAME><LINE>243</LINE><COLUMN>8</COLUMN></SFA><SFA><FILEPATH>n:\wpi\cs 502 os\z502 ws\</FILEPATH><FILENAME>z502.c</FILENAME><LINE>244</LINE><COLUMN>20</COLUMN><KEYEVENT><ID>1</ID><KIND>branch</KIND><IMPORTANCE>Full</IMPORTANCE><MESSAGE>Skip this branch, (assume 'VirtualAddress&gt;=2146435072' is false)</MESSAGE></KEYEVENT></SFA><SFA><FILEPATH>n:\wpi\cs 502 os\z502 ws\</FILEPATH><FILENAME>z502.c</FILENAME><LINE>250</LINE><COLUMN>19</COLUMN></SFA><SFA><FILEPATH>n:\wpi\cs 502 os\z502 ws\</FILEPATH><FILENAME>z502.c</FILENAME><LINE>252</LINE><COLUMN>13</COLUMN></SFA><SFA><FILEPATH>n:\wpi\cs 502 os\z502 ws\</FILEPATH><FILENAME>z502.c</FILENAME><LINE>254</LINE><COLUMN>15</COLUMN></SFA><SFA><FILEPATH>n:\wpi\cs 502 os\z502 ws\</FILEPATH><FILENAME>z502.c</FILENAME><LINE>258</LINE><COLUMN>22</COLUMN><KEYEVENT><ID>2</ID><KIND>branch</KIND><IMPORTANCE>Full</IMPORTANCE><MESSAGE>Enter this loop, (assume 'page_is_valid==(BOOL)0')</MESSAGE></KEYEVENT></SFA><SFA><FILEPATH>n:\wpi\cs 502 os\z502 ws\</FILEPATH><FILENAME>z502.c</FILENAME><LINE>259</LINE><COLUMN>13</COLUMN></SFA><SFA><FILEPATH>n:\wpi\cs 502 os\z502 ws\</FILEPATH><FILENAME>z502.c</FILENAME><LINE>260</LINE><COLUMN>24</COLUMN><KEYEVENT><ID>3</ID><KIND>branch</KIND><IMPORTANCE>Full</IMPORTANCE><MESSAGE>Skip this branch, (assume 'VirtualPageNumber&gt;=1024' is false)</MESSAGE></KEYEVENT></SFA><SFA><FILEPATH>n:\wpi\cs 502 os\z502 ws\</FILEPATH><FILENAME>z502.c</FILENAME><LINE>262</LINE><COLUMN>24</COLUMN><KEYEVENT><ID>4</ID><KIND>branch</KIND><IMPORTANCE>Full</IMPORTANCE><MESSAGE>Enter this branch, (assume 'VirtualPageNumber&lt;0')</MESSAGE></KEYEVENT></SFA><SFA><FILEPATH>n:\wpi\cs 502 os\z502 ws\</FILEPATH><FILENAME>z502.c</FILENAME><LINE>263</LINE><COLUMN>14</COLUMN></SFA><SFA><FILEPATH>n:\wpi\cs 502 os\z502 ws\</FILEPATH><FILENAME>z502.c</FILENAME><LINE>264</LINE><COLUMN>28</COLUMN><KEYEVENT><ID>5</ID><KIND>branch</KIND><IMPORTANCE>Full</IMPORTANCE><MESSAGE>Skip this branch, (assume '&lt;branch condition&gt;' is false)</MESSAGE></KEYEVENT></SFA><SFA><FILEPATH>n:\wpi\cs 502 os\z502 ws\</FILEPATH><FILENAME>z502.c</FILENAME><LINE>267</LINE><COLUMN>4</COLUMN><KEYEVENT><ID>6</ID><KIND>branch</KIND><IMPORTANCE>Full</IMPORTANCE><MESSAGE>Skip this branch, (assume '&lt;branch condition&gt;' is false)</MESSAGE></KEYEVENT></SFA><SFA><FILEPATH>n:\wpi\cs 502 os\z502 ws\</FILEPATH><FILENAME>z502.c</FILENAME><LINE>271</LINE><COLUMN>15</COLUMN></SFA><SFA><FILEPATH>n:\wpi\cs 502 os\z502 ws\</FILEPATH><FILENAME>z502.c</FILENAME><LINE>272</LINE><COLUMN>17</COLUMN><KEYEVENT><ID>7</ID><KIND>branch</KIND><IMPORTANCE>Full</IMPORTANCE><MESSAGE>Enter this branch, (assume 'invalidity&gt;0')</MESSAGE></KEYEVENT></SFA><SFA><FILEPATH>n:\wpi\cs 502 os\z502 ws\</FILEPATH><FILENAME>z502.c</FILENAME><LINE>274</LINE><COLUMN>5</COLUMN><KEYEVENT><ID>8</ID><KIND>branch</KIND><IMPORTANCE>Full</IMPORTANCE><MESSAGE>Skip this branch, (assume '&lt;branch condition&gt;' is false)</MESSAGE></KEYEVENT></SFA><SFA><FILEPATH>n:\wpi\cs 502 os\z502 ws\</FILEPATH><FILENAME>z502.c</FILENAME><LINE>281</LINE><COLUMN>40</COLUMN></SFA><SFA><FILEPATH>n:\wpi\cs 502 os\z502 ws\</FILEPATH><FILENAME>z502.c</FILENAME><LINE>283</LINE><COLUMN>14</COLUMN></SFA><SFA><FILEPATH>n:\wpi\cs 502 os\z502 ws\</FILEPATH><FILENAME>z502.c</FILENAME><LINE>284</LINE><COLUMN>16</COLUMN></SFA><SFA><FILEPATH>n:\wpi\cs 502 os\z502 ws\</FILEPATH><FILENAME>z502.c</FILENAME><LINE>286</LINE><COLUMN>10</COLUMN></SFA><SFA><FILEPATH>n:\wpi\cs 502 os\z502 ws\</FILEPATH><FILENAME>z502.c</FILENAME><LINE>258</LINE><COLUMN>22</COLUMN><KEYEVENT><ID>9</ID><KIND>branch</KIND><IMPORTANCE>Full</IMPORTANCE><MESSAGE>Enter this loop, (assume 'page_is_valid==(BOOL)0')</MESSAGE></KEYEVENT></SFA><SFA><FILEPATH>n:\wpi\cs 502 os\z502 ws\</FILEPATH><FILENAME>z502.c</FILENAME><LINE>259</LINE><COLUMN>13</COLUMN></SFA><SFA><FILEPATH>n:\wpi\cs 502 os\z502 ws\</FILEPATH><FILENAME>z502.c</FILENAME><LINE>260</LINE><COLUMN>24</COLUMN><KEYEVENT><ID>10</ID><KIND>branch</KIND><IMPORTANCE>Full</IMPORTANCE><MESSAGE>Skip this branch, (assume 'VirtualPageNumber&gt;=1024' is false)</MESSAGE></KEYEVENT></SFA><SFA><FILEPATH>n:\wpi\cs 502 os\z502 ws\</FILEPATH><FILENAME>z502.c</FILENAME><LINE>262</LINE><COLUMN>24</COLUMN><KEYEVENT><ID>11</ID><KIND>branch</KIND><IMPORTANCE>Full</IMPORTANCE><MESSAGE>Enter this branch, (assume 'VirtualPageNumber&lt;0')</MESSAGE></KEYEVENT></SFA><SFA><FILEPATH>n:\wpi\cs 502 os\z502 ws\</FILEPATH><FILENAME>z502.c</FILENAME><LINE>263</LINE><COLUMN>14</COLUMN></SFA><SFA><FILEPATH>n:\wpi\cs 502 os\z502 ws\</FILEPATH><FILENAME>z502.c</FILENAME><LINE>264</LINE><COLUMN>28</COLUMN><KEYEVENT><ID>12</ID><KIND>branch</KIND><IMPORTANCE>Full</IMPORTANCE><MESSAGE>Skip this branch, (assume '&lt;branch condition&gt;' is false)</MESSAGE></KEYEVENT></SFA><SFA><FILEPATH>n:\wpi\cs 502 os\z502 ws\</FILEPATH><FILENAME>z502.c</FILENAME><LINE>267</LINE><COLUMN>4</COLUMN><KEYEVENT><ID>13</ID><KIND>branch</KIND><IMPORTANCE>Full</IMPORTANCE><MESSAGE>Skip this branch, (assume '&lt;branch condition&gt;' is false)</MESSAGE></KEYEVENT></SFA><SFA><FILEPATH>n:\wpi\cs 502 os\z502 ws\</FILEPATH><FILENAME>z502.c</FILENAME><LINE>271</LINE><COLUMN>15</COLUMN></SFA><SFA><FILEPATH>n:\wpi\cs 502 os\z502 ws\</FILEPATH><FILENAME>z502.c</FILENAME><LINE>272</LINE><COLUMN>17</COLUMN><KEYEVENT><ID>14</ID><KIND>branch</KIND><IMPORTANCE>Full</IMPORTANCE><MESSAGE>Enter this branch, (assume 'invalidity&gt;0')</MESSAGE></KEYEVENT></SFA><SFA><FILEPATH>n:\wpi\cs 502 os\z502 ws\</FILEPATH><FILENAME>z502.c</FILENAME><LINE>274</LINE><COLUMN>5</COLUMN><KEYEVENT><ID>15</ID><KIND>branch</KIND><IMPORTANCE>Full</IMPORTANCE><MESSAGE>Skip this branch, (assume '&lt;branch condition&gt;' is false)</MESSAGE></KEYEVENT></SFA><SFA><FILEPATH>n:\wpi\cs 502 os\z502 ws\</FILEPATH><FILENAME>z502.c</FILENAME><LINE>281</LINE><COLUMN>40</COLUMN></SFA><SFA><FILEPATH>n:\wpi\cs 502 os\z502 ws\</FILEPATH><FILENAME>z502.c</FILENAME><LINE>283</LINE><COLUMN>14</COLUMN></SFA><SFA><FILEPATH>n:\wpi\cs 502 os\z502 ws\</FILEPATH><FILENAME>z502.c</FILENAME><LINE>284</LINE><COLUMN>16</COLUMN></SFA><SFA><FILEPATH>n:\wpi\cs 502 os\z502 ws\</FILEPATH><FILENAME>z502.c</FILENAME><LINE>286</LINE><COLUMN>10</COLUMN></SFA><SFA><FILEPATH>n:\wpi\cs 502 os\z502 ws\</FILEPATH><FILENAME>z502.c</FILENAME><LINE>258</LINE><COLUMN>22</COLUMN><KEYEVENT><ID>16</ID><KIND>branch</KIND><IMPORTANCE>Full</IMPORTANCE><MESSAGE>Continue this loop, (assume 'page_is_valid==(BOOL)0')</MESSAGE></KEYEVENT></SFA><SFA><FILEPATH>n:\wpi\cs 502 os\z502 ws\</FILEPATH><FILENAME>z502.c</FILENAME><LINE>291</LINE><COLUMN>9</COLUMN></SFA><SFA><FILEPATH>n:\wpi\cs 502 os\z502 ws\</FILEPATH><FILENAME>z502.c</FILENAME><LINE>292</LINE><COLUMN>20</COLUMN></SFA><SFA><FILEPATH>n:\wpi\cs 502 os\z502 ws\</FILEPATH><FILENAME>z502.c</FILENAME><LINE>293</LINE><COLUMN>20</COLUMN></SFA><SFA><FILEPATH>n:\wpi\cs 502 os\z502 ws\</FILEPATH><FILENAME>z502.c</FILENAME><LINE>294</LINE><COLUMN>20</COLUMN></SFA><SFA><FILEPATH>n:\wpi\cs 502 os\z502 ws\</FILEPATH><FILENAME>z502.c</FILENAME><LINE>295</LINE><COLUMN>20</COLUMN></SFA><SFA><FILEPATH>n:\wpi\cs 502 os\z502 ws\</FILEPATH><FILENAME>z502.c</FILENAME><LINE>297</LINE><COLUMN>15</COLUMN></SFA><SFA><FILEPATH>n:\wpi\cs 502 os\z502 ws\</FILEPATH><FILENAME>z502.c</FILENAME><LINE>298</LINE><COLUMN>17</COLUMN><KEYEVENT><ID>17</ID><KIND>branch</KIND><IMPORTANCE>Full</IMPORTANCE><MESSAGE>Skip this branch, (assume 'page_offset&gt;(short)16-4' is false)</MESSAGE></KEYEVENT></SFA><SFA><FILEPATH>n:\wpi\cs 502 os\z502 ws\</FILEPATH><FILENAME>z502.c</FILENAME><LINE>331</LINE><COLUMN>17</COLUMN></SFA><SFA><FILEPATH>n:\wpi\cs 502 os\z502 ws\</FILEPATH><FILENAME>z502.c</FILENAME><LINE>338</LINE><COLUMN>3</COLUMN></SFA><SFA><FILEPATH>n:\wpi\cs 502 os\z502 ws\</FILEPATH><FILENAME>z502.c</FILENAME><LINE>344</LINE><COLUMN>38</COLUMN></SFA><SFA><FILEPATH>n:\wpi\cs 502 os\z502 ws\</FILEPATH><FILENAME>z502.c</FILENAME><LINE>346</LINE><COLUMN>19</COLUMN><KEYEVENT><ID>18</ID><KIND>branch</KIND><IMPORTANCE>Full</IMPORTANCE><MESSAGE>Skip this branch, (assume 'read_or_write==0' is false)</MESSAGE></KEYEVENT></SFA><SFA><FILEPATH>n:\wpi\cs 502 os\z502 ws\</FILEPATH><FILENAME>z502.c</FILENAME><LINE>354</LINE><COLUMN>19</COLUMN><KEYEVENT><ID>19</ID><KIND>branch</KIND><IMPORTANCE>Full</IMPORTANCE><MESSAGE>Enter this branch, (assume 'read_or_write==1')</MESSAGE></KEYEVENT></SFA><SFA><FILEPATH>n:\wpi\cs 502 os\z502 ws\</FILEPATH><FILENAME>z502.c</FILENAME><LINE>355</LINE><COLUMN>29</COLUMN><KEYEVENT><ID>20</ID><KIND>usage</KIND><IMPORTANCE>Essential</IMPORTANCE><MESSAGE>Invalid write to 'MEMORY[32766]', (writable range is 0 to 1023)</MESSAGE></KEYEVENT></SFA></PATH></DEFECT><DEFECT><SFA><FILEPATH>n:\wpi\cs 502 os\z502 ws\</FILEPATH><FILENAME>z502.c</FILENAME><LINE>362</LINE><COLUMN>42</COLUMN></SFA><DEFECTCODE>6001</DEFECTCODE><DESCRIPTION>Using uninitialized memory 'ptbl_bits'.</DESCRIPTION><FUNCTION>MemoryCommon</FUNCTION><DECORATED>MemoryCommon</DECORATED><FUNCLINE>231</FUNCLINE><PROBABILITY>1</PROBABILITY><RANK>3</RANK><CATEGORY><RULECATEGORY>mspft</RULECATEGORY></CATEGORY><PATH><SFA><FILEPATH>n:\wpi\cs 502 os\z502 ws\</FILEPATH><FILENAME>z502.c</FILENAME><LINE>232</LINE><COLUMN>7</COLUMN></SFA><SFA><FILEPATH>n:\wpi\cs 502 os\z502 ws\</FILEPATH><FILENAME>z502.c</FILENAME><LINE>233</LINE><COLUMN>7</COLUMN></SFA><SFA><FILEPATH>n:\wpi\cs 502 os\z502 ws\</FILEPATH><FILENAME>z502.c</FILENAME><LINE>234</LINE><COLUMN>7</COLUMN></SFA><SFA><FILEPATH>n:\wpi\cs 502 os\z502 ws\</FILEPATH><FILENAME>z502.c</FILENAME><LINE>235</LINE><COLUMN>7</COLUMN></SFA><SFA><FILEPATH>n:\wpi\cs 502 os\z502 ws\</FILEPATH><FILENAME>z502.c</FILENAME><LINE>236</LINE><COLUMN>7</COLUMN></SFA><SFA><FILEPATH>n:\wpi\cs 502 os\z502 ws\</FILEPATH><FILENAME>z502.c</FILENAME><LINE>237</LINE><COLUMN>7</COLUMN><KEYEVENT><ID>1</ID><KIND>declaration</KIND><IMPORTANCE>Essential</IMPORTANCE><MESSAGE>'ptbl_bits' is not initialized</MESSAGE></KEYEVENT></SFA><SFA><FILEPATH>n:\wpi\cs 502 os\z502 ws\</FILEPATH><FILENAME>z502.c</FILENAME><LINE>238</LINE><COLUMN>7</COLUMN></SFA><SFA><FILEPATH>n:\wpi\cs 502 os\z502 ws\</FILEPATH><FILENAME>z502.c</FILENAME><LINE>239</LINE><COLUMN>6</COLUMN></SFA><SFA><FILEPATH>n:\wpi\cs 502 os\z502 ws\</FILEPATH><FILENAME>z502.c</FILENAME><LINE>240</LINE><COLUMN>6</COLUMN></SFA><SFA><FILEPATH>n:\wpi\cs 502 os\z502 ws\</FILEPATH><FILENAME>z502.c</FILENAME><LINE>242</LINE><COLUMN>7</COLUMN></SFA><SFA><FILEPATH>n:\wpi\cs 502 os\z502 ws\</FILEPATH><FILENAME>z502.c</FILENAME><LINE>243</LINE><COLUMN>8</COLUMN></SFA><SFA><FILEPATH>n:\wpi\cs 502 os\z502 ws\</FILEPATH><FILENAME>z502.c</FILENAME><LINE>244</LINE><COLUMN>20</COLUMN><KEYEVENT><ID>2</ID><KIND>branch</KIND><IMPORTANCE>Full</IMPORTANCE><MESSAGE>Skip this branch, (assume 'VirtualAddress&gt;=2146435072' is false)</MESSAGE></KEYEVENT></SFA><SFA><FILEPATH>n:\wpi\cs 502 os\z502 ws\</FILEPATH><FILENAME>z502.c</FILENAME><LINE>250</LINE><COLUMN>19</COLUMN></SFA><SFA><FILEPATH>n:\wpi\cs 502 os\z502 ws\</FILEPATH><FILENAME>z502.c</FILENAME><LINE>252</LINE><COLUMN>13</COLUMN></SFA><SFA><FILEPATH>n:\wpi\cs 502 os\z502 ws\</FILEPATH><FILENAME>z502.c</FILENAME><LINE>254</LINE><COLUMN>15</COLUMN></SFA><SFA><FILEPATH>n:\wpi\cs 502 os\z502 ws\</FILEPATH><FILENAME>z502.c</FILENAME><LINE>258</LINE><COLUMN>22</COLUMN><KEYEVENT><ID>3</ID><KIND>branch</KIND><IMPORTANCE>Full</IMPORTANCE><MESSAGE>Enter this loop, (assume 'page_is_valid==(BOOL)0')</MESSAGE></KEYEVENT></SFA><SFA><FILEPATH>n:\wpi\cs 502 os\z502 ws\</FILEPATH><FILENAME>z502.c</FILENAME><LINE>259</LINE><COLUMN>13</COLUMN></SFA><SFA><FILEPATH>n:\wpi\cs 502 os\z502 ws\</FILEPATH><FILENAME>z502.c</FILENAME><LINE>260</LINE><COLUMN>24</COLUMN><KEYEVENT><ID>4</ID><KIND>branch</KIND><IMPORTANCE>Full</IMPORTANCE><MESSAGE>Skip this branch, (assume 'VirtualPageNumber&gt;=1024' is false)</MESSAGE></KEYEVENT></SFA><SFA><FILEPATH>n:\wpi\cs 502 os\z502 ws\</FILEPATH><FILENAME>z502.c</FILENAME><LINE>262</LINE><COLUMN>24</COLUMN><KEYEVENT><ID>5</ID><KIND>branch</KIND><IMPORTANCE>Full</IMPORTANCE><MESSAGE>Enter this branch, (assume 'VirtualPageNumber&lt;0')</MESSAGE></KEYEVENT></SFA><SFA><FILEPATH>n:\wpi\cs 502 os\z502 ws\</FILEPATH><FILENAME>z502.c</FILENAME><LINE>263</LINE><COLUMN>14</COLUMN></SFA><SFA><FILEPATH>n:\wpi\cs 502 os\z502 ws\</FILEPATH><FILENAME>z502.c</FILENAME><LINE>264</LINE><COLUMN>28</COLUMN><KEYEVENT><ID>6</ID><KIND>branch</KIND><IMPORTANCE>Full</IMPORTANCE><MESSAGE>Skip this branch, (assume '&lt;branch condition&gt;' is false)</MESSAGE></KEYEVENT></SFA><SFA><FILEPATH>n:\wpi\cs 502 os\z502 ws\</FILEPATH><FILENAME>z502.c</FILENAME><LINE>267</LINE><COLUMN>4</COLUMN><KEYEVENT><ID>7</ID><KIND>branch</KIND><IMPORTANCE>Full</IMPORTANCE><MESSAGE>Skip this branch, (assume '&lt;branch condition&gt;' is false)</MESSAGE></KEYEVENT></SFA><SFA><FILEPATH>n:\wpi\cs 502 os\z502 ws\</FILEPATH><FILENAME>z502.c</FILENAME><LINE>271</LINE><COLUMN>15</COLUMN></SFA><SFA><FILEPATH>n:\wpi\cs 502 os\z502 ws\</FILEPATH><FILENAME>z502.c</FILENAME><LINE>272</LINE><COLUMN>17</COLUMN><KEYEVENT><ID>8</ID><KIND>branch</KIND><IMPORTANCE>Full</IMPORTANCE><MESSAGE>Enter this branch, (assume 'invalidity&gt;0')</MESSAGE></KEYEVENT></SFA><SFA><FILEPATH>n:\wpi\cs 502 os\z502 ws\</FILEPATH><FILENAME>z502.c</FILENAME><LINE>274</LINE><COLUMN>5</COLUMN><KEYEVENT><ID>9</ID><KIND>branch</KIND><IMPORTANCE>Full</IMPORTANCE><MESSAGE>Skip this branch, (assume '&lt;branch condition&gt;' is false)</MESSAGE></KEYEVENT></SFA><SFA><FILEPATH>n:\wpi\cs 502 os\z502 ws\</FILEPATH><FILENAME>z502.c</FILENAME><LINE>281</LINE><COLUMN>40</COLUMN></SFA><SFA><FILEPATH>n:\wpi\cs 502 os\z502 ws\</FILEPATH><FILENAME>z502.c</FILENAME><LINE>283</LINE><COLUMN>14</COLUMN></SFA><SFA><FILEPATH>n:\wpi\cs 502 os\z502 ws\</FILEPATH><FILENAME>z502.c</FILENAME><LINE>284</LINE><COLUMN>16</COLUMN></SFA><SFA><FILEPATH>n:\wpi\cs 502 os\z502 ws\</FILEPATH><FILENAME>z502.c</FILENAME><LINE>286</LINE><COLUMN>10</COLUMN></SFA><SFA><FILEPATH>n:\wpi\cs 502 os\z502 ws\</FILEPATH><FILENAME>z502.c</FILENAME><LINE>258</LINE><COLUMN>22</COLUMN><KEYEVENT><ID>10</ID><KIND>branch</KIND><IMPORTANCE>Full</IMPORTANCE><MESSAGE>Enter this loop, (assume 'page_is_valid==(BOOL)0')</MESSAGE></KEYEVENT></SFA><SFA><FILEPATH>n:\wpi\cs 502 os\z502 ws\</FILEPATH><FILENAME>z502.c</FILENAME><LINE>259</LINE><COLUMN>13</COLUMN></SFA><SFA><FILEPATH>n:\wpi\cs 502 os\z502 ws\</FILEPATH><FILENAME>z502.c</FILENAME><LINE>260</LINE><COLUMN>24</COLUMN><KEYEVENT><ID>11</ID><KIND>branch</KIND><IMPORTANCE>Full</IMPORTANCE><MESSAGE>Skip this branch, (assume 'VirtualPageNumber&gt;=1024' is false)</MESSAGE></KEYEVENT></SFA><SFA><FILEPATH>n:\wpi\cs 502 os\z502 ws\</FILEPATH><FILENAME>z502.c</FILENAME><LINE>262</LINE><COLUMN>24</COLUMN><KEYEVENT><ID>12</ID><KIND>branch</KIND><IMPORTANCE>Full</IMPORTANCE><MESSAGE>Enter this branch, (assume 'VirtualPageNumber&lt;0')</MESSAGE></KEYEVENT></SFA><SFA><FILEPATH>n:\wpi\cs 502 os\z502 ws\</FILEPATH><FILENAME>z502.c</FILENAME><LINE>263</LINE><COLUMN>14</COLUMN></SFA><SFA><FILEPATH>n:\wpi\cs 502 os\z502 ws\</FILEPATH><FILENAME>z502.c</FILENAME><LINE>264</LINE><COLUMN>28</COLUMN><KEYEVENT><ID>13</ID><KIND>branch</KIND><IMPORTANCE>Full</IMPORTANCE><MESSAGE>Skip this branch, (assume '&lt;branch condition&gt;' is false)</MESSAGE></KEYEVENT></SFA><SFA><FILEPATH>n:\wpi\cs 502 os\z502 ws\</FILEPATH><FILENAME>z502.c</FILENAME><LINE>267</LINE><COLUMN>4</COLUMN><KEYEVENT><ID>14</ID><KIND>branch</KIND><IMPORTANCE>Full</IMPORTANCE><MESSAGE>Skip this branch, (assume '&lt;branch condition&gt;' is false)</MESSAGE></KEYEVENT></SFA><SFA><FILEPATH>n:\wpi\cs 502 os\z502 ws\</FILEPATH><FILENAME>z502.c</FILENAME><LINE>271</LINE><COLUMN>15</COLUMN></SFA><SFA><FILEPATH>n:\wpi\cs 502 os\z502 ws\</FILEPATH><FILENAME>z502.c</FILENAME><LINE>272</LINE><COLUMN>17</COLUMN><KEYEVENT><ID>15</ID><KIND>branch</KIND><IMPORTANCE>Full</IMPORTANCE><MESSAGE>Enter this branch, (assume 'invalidity&gt;0')</MESSAGE></KEYEVENT></SFA><SFA><FILEPATH>n:\wpi\cs 502 os\z502 ws\</FILEPATH><FILENAME>z502.c</FILENAME><LINE>274</LINE><COLUMN>5</COLUMN><KEYEVENT><ID>16</ID><KIND>branch</KIND><IMPORTANCE>Full</IMPORTANCE><MESSAGE>Skip this branch, (assume '&lt;branch condition&gt;' is false)</MESSAGE></KEYEVENT></SFA><SFA><FILEPATH>n:\wpi\cs 502 os\z502 ws\</FILEPATH><FILENAME>z502.c</FILENAME><LINE>281</LINE><COLUMN>40</COLUMN></SFA><SFA><FILEPATH>n:\wpi\cs 502 os\z502 ws\</FILEPATH><FILENAME>z502.c</FILENAME><LINE>283</LINE><COLUMN>14</COLUMN></SFA><SFA><FILEPATH>n:\wpi\cs 502 os\z502 ws\</FILEPATH><FILENAME>z502.c</FILENAME><LINE>284</LINE><COLUMN>16</COLUMN></SFA><SFA><FILEPATH>n:\wpi\cs 502 os\z502 ws\</FILEPATH><FILENAME>z502.c</FILENAME><LINE>286</LINE><COLUMN>10</COLUMN></SFA><SFA><FILEPATH>n:\wpi\cs 502 os\z502 ws\</FILEPATH><FILENAME>z502.c</FILENAME><LINE>258</LINE><COLUMN>22</COLUMN><KEYEVENT><ID>17</ID><KIND>branch</KIND><IMPORTANCE>Full</IMPORTANCE><MESSAGE>Continue this loop, (assume 'page_is_valid==(BOOL)0')</MESSAGE></KEYEVENT></SFA><SFA><FILEPATH>n:\wpi\cs 502 os\z502 ws\</FILEPATH><FILENAME>z502.c</FILENAME><LINE>291</LINE><COLUMN>9</COLUMN></SFA><SFA><FILEPATH>n:\wpi\cs 502 os\z502 ws\</FILEPATH><FILENAME>z502.c</FILENAME><LINE>292</LINE><COLUMN>20</COLUMN></SFA><SFA><FILEPATH>n:\wpi\cs 502 os\z502 ws\</FILEPATH><FILENAME>z502.c</FILENAME><LINE>293</LINE><COLUMN>20</COLUMN></SFA><SFA><FILEPATH>n:\wpi\cs 502 os\z502 ws\</FILEPATH><FILENAME>z502.c</FILENAME><LINE>294</LINE><COLUMN>20</COLUMN></SFA><SFA><FILEPATH>n:\wpi\cs 502 os\z502 ws\</FILEPATH><FILENAME>z502.c</FILENAME><LINE>295</LINE><COLUMN>20</COLUMN></SFA><SFA><FILEPATH>n:\wpi\cs 502 os\z502 ws\</FILEPATH><FILENAME>z502.c</FILENAME><LINE>297</LINE><COLUMN>15</COLUMN></SFA><SFA><FILEPATH>n:\wpi\cs 502 os\z502 ws\</FILEPATH><FILENAME>z502.c</FILENAME><LINE>298</LINE><COLUMN>17</COLUMN><KEYEVENT><ID>18</ID><KIND>branch</KIND><IMPORTANCE>Full</IMPORTANCE><MESSAGE>Skip this branch, (assume 'page_offset&gt;(short)16-4' is false)</MESSAGE></KEYEVENT></SFA><SFA><FILEPATH>n:\wpi\cs 502 os\z502 ws\</FILEPATH><FILENAME>z502.c</FILENAME><LINE>331</LINE><COLUMN>17</COLUMN></SFA><SFA><FILEPATH>n:\wpi\cs 502 os\z502 ws\</FILEPATH><FILENAME>z502.c</FILENAME><LINE>338</LINE><COLUMN>3</COLUMN></SFA><SFA><FILEPATH>n:\wpi\cs 502 os\z502 ws\</FILEPATH><FILENAME>z502.c</FILENAME><LINE>344</LINE><COLUMN>38</COLUMN></SFA><SFA><FILEPATH>n:\wpi\cs 502 os\z502 ws\</FILEPATH><FILENAME>z502.c</FILENAME><LINE>346</LINE><COLUMN>19</COLUMN><KEYEVENT><ID>19</ID><KIND>branch</KIND><IMPORTANCE>Full</IMPORTANCE><MESSAGE>Skip this branch, (assume 'read_or_write==0' is false)</MESSAGE></KEYEVENT></SFA><SFA><FILEPATH>n:\wpi\cs 502 os\z502 ws\</FILEPATH><FILENAME>z502.c</FILENAME><LINE>354</LINE><COLUMN>19</COLUMN><KEYEVENT><ID>20</ID><KIND>branch</KIND><IMPORTANCE>Full</IMPORTANCE><MESSAGE>Skip this branch, (assume 'read_or_write==1' is false)</MESSAGE></KEYEVENT></SFA><SFA><FILEPATH>n:\wpi\cs 502 os\z502 ws\</FILEPATH><FILENAME>z502.c</FILENAME><LINE>362</LINE><COLUMN>42</COLUMN><KEYEVENT><ID>21</ID><KIND>usage</KIND><IMPORTANCE>Essential</IMPORTANCE><MESSAGE>'ptbl_bits' is used, but may not have been initialized</MESSAGE></KEYEVENT></SFA></PATH></DEFECT><DEFECT><SFA><FILEPATH>n:\wpi\cs 502 os\z502 ws\</FILEPATH><FILENAME>z502.c</FILENAME><LINE>379</LINE><COLUMN>21</COLUMN></SFA><DEFECTCODE>6326</DEFECTCODE><DESCRIPTION>Potential comparison of a constant with another constant.</DESCRIPTION><FUNCTION>DoMemoryDebug</FUNCTION><DECORATED>DoMemoryDebug</DECORATED><FUNCLINE>378</FUNCLINE><PATH/></DEFECT><DEFECT><SFA><FILEPATH>n:\wpi\cs 502 os\z502 ws\</FILEPATH><FILENAME>z502.c</FILENAME><LINE>862</LINE><COLUMN>9</COLUMN></SFA><DEFECTCODE>6340</DEFECTCODE><DESCRIPTION>Mismatch on sign: 'unsigned int' passed as _Param_(2) when some signed type is required in call to 'printf'.</DESCRIPTION><FUNCTION>HardwareReadDisk</FUNCTION><DECORATED>HardwareReadDisk</DECORATED><FUNCLINE>807</FUNCLINE><PATH/></DEFECT><DEFECT><SFA><FILEPATH>n:\wpi\cs 502 os\z502 ws\</FILEPATH><FILENAME>z502.c</FILENAME><LINE>947</LINE><COLUMN>9</COLUMN></SFA><DEFECTCODE>6340</DEFECTCODE><DESCRIPTION>Mismatch on sign: 'unsigned int' passed as _Param_(2) when some signed type is required in call to 'printf'.</DESCRIPTION><FUNCTION>HardwareWriteDisk</FUNCTION><DECORATED>HardwareWriteDisk</DECORATED><FUNCLINE>896</FUNCLINE><PATH/></DEFECT><DEFECT><SFA><FILEPATH>n:\wpi\cs 502 os\z502 ws\</FILEPATH><FILENAME>z502.c</FILENAME><LINE>1007</LINE><COLUMN>9</COLUMN></SFA><DEFECTCODE>6340</DEFECTCODE><DESCRIPTION>Mismatch on sign: 'unsigned int' passed as _Param_(2) when some signed type is required in call to 'printf'.</DESCRIPTION><FUNCTION>HardwareTimer</FUNCTION><DECORATED>HardwareTimer</DECORATED><FUNCLINE>976</FUNCLINE><PATH/></DEFECT><DEFECT><SFA><FILEPATH>n:\wpi\cs 502 os\z502 ws\</FILEPATH><FILENAME>z502.c</FILENAME><LINE>1007</LINE><COLUMN>9</COLUMN></SFA><DEFECTCODE>6340</DEFECTCODE><DESCRIPTION>Mismatch on sign: 'unsigned int' passed as _Param_(3) when some signed type is required in call to 'printf'.</DESCRIPTION><FUNCTION>HardwareTimer</FUNCTION><DECORATED>HardwareTimer</DECORATED><FUNCLINE>976</FUNCLINE><PATH/></DEFECT><DEFECT><SFA><FILEPATH>n:\wpi\cs 502 os\z502 ws\</FILEPATH><FILENAME>z502.c</FILENAME><LINE>1013</LINE><COLUMN>8</COLUMN></SFA><DEFECTCODE>6340</DEFECTCODE><DESCRIPTION>Mismatch on sign: 'unsigned int' passed as _Param_(2) when some signed type is required in call to 'printf'.</DESCRIPTION><FUNCTION>HardwareTimer</FUNCTION><DECORATED>HardwareTimer</DECORATED><FUNCLINE>976</FUNCLINE><PATH/></DEFECT><DEFECT><SFA><FILEPATH>n:\wpi\cs 502 os\z502 ws\</FILEPATH><FILENAME>z502.c</FILENAME><LINE>1013</LINE><COLUMN>8</COLUMN></SFA><DEFECTCODE>6340</DEFECTCODE><DESCRIPTION>Mismatch on sign: 'unsigned int' passed as _Param_(4) when some signed type is required in call to 'printf'.</DESCRIPTION><FUNCTION>HardwareTimer</FUNCTION><DECORATED>HardwareTimer</DECORATED><FUNCLINE>976</FUNCLINE><PATH/></DEFECT><DEFECT><SFA><FILEPATH>n:\wpi\cs 502 os\z502 ws\</FILEPATH><FILENAME>z502.c</FILENAME><LINE>1087</LINE><COLUMN>7</COLUMN></SFA><DEFECTCODE>6340</DEFECTCODE><DESCRIPTION>Mismatch on sign: 'unsigned int' passed as _Param_(2) when some signed type is required in call to 'printf'.</DESCRIPTION><FUNCTION>HaltSimulation</FUNCTION><DECORATED>HaltSimulation</DECORATED><FUNCLINE>1079</FUNCLINE><PATH/></DEFECT><DEFECT><SFA><FILEPATH>n:\wpi\cs 502 os\z502 ws\</FILEPATH><FILENAME>z502.c</FILENAME><LINE>1118</LINE><COLUMN>8</COLUMN></SFA><DEFECTCODE>6340</DEFECTCODE><DESCRIPTION>Mismatch on sign: 'unsigned int' passed as _Param_(2) when some signed type is required in call to 'printf'.</DESCRIPTION><FUNCTION>IdleSimulation</FUNCTION><DECORATED>IdleSimulation</DECORATED><FUNCLINE>1104</FUNCLINE><PATH/></DEFECT><DEFECT><SFA><FILEPATH>n:\wpi\cs 502 os\z502 ws\</FILEPATH><FILENAME>z502.c</FILENAME><LINE>1195</LINE><COLUMN>22</COLUMN></SFA><DEFECTCODE>6011</DEFECTCODE><DESCRIPTION>Dereferencing NULL pointer 'our_ptr'. </DESCRIPTION><FUNCTION>MakeContext</FUNCTION><DECORATED>MakeContext</DECORATED><FUNCLINE>1165</FUNCLINE><PROBABILITY>1</PROBABILITY><RANK>4</RANK><CATEGORY><RULECATEGORY>mspft</RULECATEGORY></CATEGORY><PATH><SFA><FILEPATH>n:\wpi\cs 502 os\z502 ws\</FILEPATH><FILENAME>z502.c</FILENAME><LINE>1167</LINE><COLUMN>14</COLUMN></SFA><SFA><FILEPATH>n:\wpi\cs 502 os\z502 ws\</FILEPATH><FILENAME>z502.c</FILENAME><LINE>1168</LINE><COLUMN>5</COLUMN></SFA><SFA><FILEPATH>n:\wpi\cs 502 os\z502 ws\</FILEPATH><FILENAME>z502.c</FILENAME><LINE>1170</LINE><COLUMN>21</COLUMN></SFA><SFA><FILEPATH>n:\wpi\cs 502 os\z502 ws\</FILEPATH><FILENAME>z502.c</FILENAME><LINE>1174</LINE><COLUMN>8</COLUMN></SFA><SFA><FILEPATH>n:\wpi\cs 502 os\z502 ws\</FILEPATH><FILENAME>z502.c</FILENAME><LINE>1176</LINE><COLUMN>30</COLUMN></SFA><SFA><FILEPATH>n:\wpi\cs 502 os\z502 ws\</FILEPATH><FILENAME>z502.c</FILENAME><LINE>1181</LINE><COLUMN>9</COLUMN><KEYEVENT><ID>1</ID><KIND>declaration</KIND><IMPORTANCE>Essential</IMPORTANCE><MESSAGE>'our_ptr' may be NULL</MESSAGE></KEYEVENT></SFA><SFA><FILEPATH>n:\wpi\cs 502 os\z502 ws\</FILEPATH><FILENAME>z502.c</FILENAME><LINE>1182</LINE><COLUMN>13</COLUMN><KEYEVENT><ID>2</ID><KIND>branch</KIND><IMPORTANCE>Full</IMPORTANCE><MESSAGE>Enter this branch, (assume 'our_ptr==(((void *)0))')</MESSAGE></KEYEVENT></SFA><SFA><FILEPATH>n:\wpi\cs 502 os\z502 ws\</FILEPATH><FILENAME>z502.c</FILENAME><LINE>1183</LINE><COLUMN>8</COLUMN></SFA><SFA><FILEPATH>n:\wpi\cs 502 os\z502 ws\</FILEPATH><FILENAME>z502.c</FILENAME><LINE>1184</LINE><COLUMN>23</COLUMN></SFA><SFA><FILEPATH>n:\wpi\cs 502 os\z502 ws\</FILEPATH><FILENAME>z502.c</FILENAME><LINE>1191</LINE><COLUMN>11</COLUMN></SFA><SFA><FILEPATH>n:\wpi\cs 502 os\z502 ws\</FILEPATH><FILENAME>z502.c</FILENAME><LINE>1192</LINE><COLUMN>34</COLUMN></SFA><SFA><FILEPATH>n:\wpi\cs 502 os\z502 ws\</FILEPATH><FILENAME>z502.c</FILENAME><LINE>1195</LINE><COLUMN>22</COLUMN><KEYEVENT><ID>3</ID><KIND>usage</KIND><IMPORTANCE>Essential</IMPORTANCE><MESSAGE>'our_ptr' is dereferenced, but may still be NULL</MESSAGE></KEYEVENT></SFA></PATH></DEFECT><DEFECT><SFA><FILEPATH>n:\wpi\cs 502 os\z502 ws\</FILEPATH><FILENAME>z502.c</FILENAME><LINE>1383</LINE><COLUMN>38</COLUMN></SFA><DEFECTCODE>6386</DEFECTCODE><DESCRIPTION>Buffer overrun while writing to 'ThreadTable':  the writable size is '840' bytes, but '-28' bytes might be written.</DESCRIPTION><FUNCTION>SwitchContext</FUNCTION><DECORATED>SwitchContext</DECORATED><FUNCLINE>1279</FUNCLINE><PROBABILITY>1</PROBABILITY><RANK>4</RANK><CATEGORY><RULECATEGORY>mspft</RULECATEGORY></CATEGORY><PATH><SFA><FILEPATH>n:\wpi\cs 502 os\z502 ws\</FILEPATH><FILENAME>z502.c</FILENAME><LINE>1280</LINE><COLUMN>14</COLUMN></SFA><SFA><FILEPATH>n:\wpi\cs 502 os\z502 ws\</FILEPATH><FILENAME>z502.c</FILENAME><LINE>1281</LINE><COLUMN>14</COLUMN></SFA><SFA><FILEPATH>n:\wpi\cs 502 os\z502 ws\</FILEPATH><FILENAME>z502.c</FILENAME><LINE>1282</LINE><COLUMN>15</COLUMN></SFA><SFA><FILEPATH>n:\wpi\cs 502 os\z502 ws\</FILEPATH><FILENAME>z502.c</FILENAME><LINE>1283</LINE><COLUMN>5</COLUMN><KEYEVENT><ID>1</ID><KIND>declaration</KIND><IMPORTANCE>Essential</IMPORTANCE><MESSAGE>'ourLocalID' is equal to -1</MESSAGE></KEYEVENT></SFA><SFA><FILEPATH>n:\wpi\cs 502 os\z502 ws\</FILEPATH><FILENAME>z502.c</FILENAME><LINE>1284</LINE><COLUMN>5</COLUMN></SFA><SFA><FILEPATH>n:\wpi\cs 502 os\z502 ws\</FILEPATH><FILENAME>z502.c</FILENAME><LINE>1286</LINE><COLUMN>8</COLUMN></SFA><SFA><FILEPATH>n:\wpi\cs 502 os\z502 ws\</FILEPATH><FILENAME>z502.c</FILENAME><LINE>1289</LINE><COLUMN>33</COLUMN><KEYEVENT><ID>2</ID><KIND>branch</KIND><IMPORTANCE>Full</IMPORTANCE><MESSAGE>Skip this branch, (assume '&lt;branch condition&gt;' is false)</MESSAGE></KEYEVENT></SFA><SFA><FILEPATH>n:\wpi\cs 502 os\z502 ws\</FILEPATH><FILENAME>z502.c</FILENAME><LINE>1296</LINE><COLUMN>20</COLUMN><KEYEVENT><ID>3</ID><KIND>branch</KIND><IMPORTANCE>Full</IMPORTANCE><MESSAGE>Skip this branch, (assume 'DoStartSuspend!=(short)0' is false)</MESSAGE></KEYEVENT></SFA><SFA><FILEPATH>n:\wpi\cs 502 os\z502 ws\</FILEPATH><FILENAME>z502.c</FILENAME><LINE>1311</LINE><COLUMN>12</COLUMN></SFA><SFA><FILEPATH>n:\wpi\cs 502 os\z502 ws\</FILEPATH><FILENAME>z502.c</FILENAME><LINE>1312</LINE><COLUMN>21</COLUMN></SFA><SFA><FILEPATH>n:\wpi\cs 502 os\z502 ws\</FILEPATH><FILENAME>z502.c</FILENAME><LINE>1313</LINE><COLUMN>38</COLUMN></SFA><SFA><FILEPATH>n:\wpi\cs 502 os\z502 ws\</FILEPATH><FILENAME>z502.c</FILENAME><LINE>1315</LINE><COLUMN>21</COLUMN><KEYEVENT><ID>4</ID><KIND>branch</KIND><IMPORTANCE>Full</IMPORTANCE><MESSAGE>Skip this branch, (assume 'DoStartSuspend==(short)1' is false)</MESSAGE></KEYEVENT></SFA><SFA><FILEPATH>n:\wpi\cs 502 os\z502 ws\</FILEPATH><FILENAME>z502.c</FILENAME><LINE>1318</LINE><COLUMN>21</COLUMN></SFA><SFA><FILEPATH>n:\wpi\cs 502 os\z502 ws\</FILEPATH><FILENAME>z502.c</FILENAME><LINE>1322</LINE><COLUMN>53</COLUMN></SFA><SFA><FILEPATH>n:\wpi\cs 502 os\z502 ws\</FILEPATH><FILENAME>z502.c</FILENAME><LINE>1323</LINE><COLUMN>31</COLUMN></SFA><SFA><FILEPATH>n:\wpi\cs 502 os\z502 ws\</FILEPATH><FILENAME>z502.c</FILENAME><LINE>1332</LINE><COLUMN>16</COLUMN><KEYEVENT><ID>5</ID><KIND>branch</KIND><IMPORTANCE>Full</IMPORTANCE><MESSAGE>Skip this branch, (assume 'CallersPtr==*TargetContextPtr' is false)</MESSAGE></KEYEVENT></SFA><SFA><FILEPATH>n:\wpi\cs 502 os\z502 ws\</FILEPATH><FILENAME>z502.c</FILENAME><LINE>1341</LINE><COLUMN>25</COLUMN></SFA><SFA><FILEPATH>n:\wpi\cs 502 os\z502 ws\</FILEPATH><FILENAME>z502.c</FILENAME><LINE>1352</LINE><COLUMN>16</COLUMN></SFA><SFA><FILEPATH>n:\wpi\cs 502 os\z502 ws\</FILEPATH><FILENAME>z502.c</FILENAME><LINE>1356</LINE><COLUMN>18</COLUMN></SFA><SFA><FILEPATH>n:\wpi\cs 502 os\z502 ws\</FILEPATH><FILENAME>z502.c</FILENAME><LINE>1364</LINE><COLUMN>20</COLUMN><KEYEVENT><ID>6</ID><KIND>branch</KIND><IMPORTANCE>Full</IMPORTANCE><MESSAGE>Skip this branch, (assume 'DoStartSuspend==(short)1' is false)</MESSAGE></KEYEVENT></SFA><SFA><FILEPATH>n:\wpi\cs 502 os\z502 ws\</FILEPATH><FILENAME>z502.c</FILENAME><LINE>1371</LINE><COLUMN>20</COLUMN></SFA><SFA><FILEPATH>n:\wpi\cs 502 os\z502 ws\</FILEPATH><FILENAME>z502.c</FILENAME><LINE>1382</LINE><COLUMN>12</COLUMN></SFA><SFA><FILEPATH>n:\wpi\cs 502 os\z502 ws\</FILEPATH><FILENAME>z502.c</FILENAME><LINE>1383</LINE><COLUMN>38</COLUMN><KEYEVENT><ID>7</ID><KIND>usage</KIND><IMPORTANCE>Essential</IMPORTANCE><MESSAGE>Invalid write to 'ThreadTable[-1]', (writable range is 0 to 29)</MESSAGE></KEYEVENT></SFA></PATH></DEFECT><DEFECT><SFA><FILEPATH>n:\wpi\cs 502 os\z502 ws\</FILEPATH><FILENAME>z502.c</FILENAME><LINE>1530</LINE><COLUMN>10</COLUMN></SFA><DEFECTCODE>6340</DEFECTCODE><DESCRIPTION>Mismatch on sign: 'unsigned int' passed as _Param_(2) when some signed type is required in call to 'printf'.</DESCRIPTION><FUNCTION>HardwareInterrupt</FUNCTION><DECORATED>HardwareInterrupt</DECORATED><FUNCLINE>1509</FUNCLINE><PATH/></DEFECT><DEFECT><SFA><FILEPATH>n:\wpi\cs 502 os\z502 ws\</FILEPATH><FILENAME>z502.c</FILENAME><LINE>1615</LINE><COLUMN>9</COLUMN></SFA><DEFECTCODE>6340</DEFECTCODE><DESCRIPTION>Mismatch on sign: 'unsigned int' passed as _Param_(2) when some signed type is required in call to 'printf'.</DESCRIPTION><FUNCTION>HardwareInterrupt</FUNCTION><DECORATED>HardwareInterrupt</DECORATED><FUNCLINE>1509</FUNCLINE><PATH/></DEFECT><DEFECT><SFA><FILEPATH>n:\wpi\cs 502 os\z502 ws\</FILEPATH><FILENAME>z502.c</FILENAME><LINE>1611</LINE><COLUMN>37</COLUMN></SFA><DEFECTCODE>6386</DEFECTCODE><DESCRIPTION>Buffer overrun while writing to 'STAT_VECTOR[(short)1]':  the writable size is '52' bytes, but 'event_type' bytes might be written.</DESCRIPTION><FUNCTION>HardwareInterrupt</FUNCTION><DECORATED>HardwareInterrupt</DECORATED><FUNCLINE>1509</FUNCLINE><PROBABILITY>1</PROBABILITY><RANK>4</RANK><CATEGORY><RULECATEGORY>mspft</RULECATEGORY></CATEGORY><PATH><SFA><FILEPATH>n:\wpi\cs 502 os\z502 ws\</FILEPATH><FILENAME>z502.c</FILENAME><LINE>1510</LINE><COLUMN>7</COLUMN></SFA><SFA><FILEPATH>n:\wpi\cs 502 os\z502 ws\</FILEPATH><FILENAME>z502.c</FILENAME><LINE>1511</LINE><COLUMN>7</COLUMN></SFA><SFA><FILEPATH>n:\wpi\cs 502 os\z502 ws\</FILEPATH><FILENAME>z502.c</FILENAME><LINE>1512</LINE><COLUMN>7</COLUMN></SFA><SFA><FILEPATH>n:\wpi\cs 502 os\z502 ws\</FILEPATH><FILENAME>z502.c</FILENAME><LINE>1513</LINE><COLUMN>7</COLUMN></SFA><SFA><FILEPATH>n:\wpi\cs 502 os\z502 ws\</FILEPATH><FILENAME>z502.c</FILENAME><LINE>1514</LINE><COLUMN>7</COLUMN></SFA><SFA><FILEPATH>n:\wpi\cs 502 os\z502 ws\</FILEPATH><FILENAME>z502.c</FILENAME><LINE>1515</LINE><COLUMN>8</COLUMN></SFA><SFA><FILEPATH>n:\wpi\cs 502 os\z502 ws\</FILEPATH><FILENAME>z502.c</FILENAME><LINE>1516</LINE><COLUMN>6</COLUMN></SFA><SFA><FILEPATH>n:\wpi\cs 502 os\z502 ws\</FILEPATH><FILENAME>z502.c</FILENAME><LINE>1518</LINE><COLUMN>14</COLUMN></SFA><SFA><FILEPATH>n:\wpi\cs 502 os\z502 ws\</FILEPATH><FILENAME>z502.c</FILENAME><LINE>1519</LINE><COLUMN>8</COLUMN><KEYEVENT><ID>1</ID><KIND>branch</KIND><IMPORTANCE>Full</IMPORTANCE><MESSAGE>Enter this loop, (assume '1')</MESSAGE></KEYEVENT></SFA><SFA><FILEPATH>n:\wpi\cs 502 os\z502 ws\</FILEPATH><FILENAME>z502.c</FILENAME><LINE>1520</LINE><COLUMN>18</COLUMN></SFA><SFA><FILEPATH>n:\wpi\cs 502 os\z502 ws\</FILEPATH><FILENAME>z502.c</FILENAME><LINE>1522</LINE><COLUMN>4</COLUMN><KEYEVENT><ID>2</ID><KIND>branch</KIND><IMPORTANCE>Full</IMPORTANCE><MESSAGE>Skip this loop, (assume '&lt;branch condition&gt;' is false)</MESSAGE></KEYEVENT></SFA><SFA><FILEPATH>n:\wpi\cs 502 os\z502 ws\</FILEPATH><FILENAME>z502.c</FILENAME><LINE>1537</LINE><COLUMN>9</COLUMN></SFA><SFA><FILEPATH>n:\wpi\cs 502 os\z502 ws\</FILEPATH><FILENAME>z502.c</FILENAME><LINE>1538</LINE><COLUMN>27</COLUMN></SFA><SFA><FILEPATH>n:\wpi\cs 502 os\z502 ws\</FILEPATH><FILENAME>z502.c</FILENAME><LINE>1539</LINE><COLUMN>21</COLUMN></SFA><SFA><FILEPATH>n:\wpi\cs 502 os\z502 ws\</FILEPATH><FILENAME>z502.c</FILENAME><LINE>1541</LINE><COLUMN>18</COLUMN></SFA><SFA><FILEPATH>n:\wpi\cs 502 os\z502 ws\</FILEPATH><FILENAME>z502.c</FILENAME><LINE>1548</LINE><COLUMN>4</COLUMN><KEYEVENT><ID>3</ID><KIND>branch</KIND><IMPORTANCE>Full</IMPORTANCE><MESSAGE>Skip this branch, (assume '&lt;branch condition&gt;' is false)</MESSAGE></KEYEVENT></SFA><SFA><FILEPATH>n:\wpi\cs 502 os\z502 ws\</FILEPATH><FILENAME>z502.c</FILENAME><LINE>1599</LINE><COLUMN>36</COLUMN><KEYEVENT><ID>4</ID><KIND>branch</KIND><IMPORTANCE>Full</IMPORTANCE><MESSAGE>'event_type' may equal 4 (Skip this branch)</MESSAGE></KEYEVENT></SFA><SFA><FILEPATH>n:\wpi\cs 502 os\z502 ws\</FILEPATH><FILENAME>z502.c</FILENAME><LINE>1610</LINE><COLUMN>38</COLUMN></SFA><SFA><FILEPATH>n:\wpi\cs 502 os\z502 ws\</FILEPATH><FILENAME>z502.c</FILENAME><LINE>1611</LINE><COLUMN>37</COLUMN><KEYEVENT><ID>5</ID><KIND>usage</KIND><IMPORTANCE>Essential</IMPORTANCE><MESSAGE>Invalid write to 'STAT_VECTOR[(short)1][13]', (writable range is 0 to 12)</MESSAGE></KEYEVENT></SFA></PATH></DEFECT><DEFECT><SFA><FILEPATH>n:\wpi\cs 502 os\z502 ws\</FILEPATH><FILENAME>z502.c</FILENAME><LINE>1610</LINE><COLUMN>38</COLUMN></SFA><DEFECTCODE>6386</DEFECTCODE><DESCRIPTION>Buffer overrun while writing to 'STAT_VECTOR[(short)0]':  the writable size is '52' bytes, but 'event_type' bytes might be written.</DESCRIPTION><FUNCTION>HardwareInterrupt</FUNCTION><DECORATED>HardwareInterrupt</DECORATED><FUNCLINE>1509</FUNCLINE><PROBABILITY>1</PROBABILITY><RANK>4</RANK><CATEGORY><RULECATEGORY>mspft</RULECATEGORY></CATEGORY><PATH><SFA><FILEPATH>n:\wpi\cs 502 os\z502 ws\</FILEPATH><FILENAME>z502.c</FILENAME><LINE>1510</LINE><COLUMN>7</COLUMN></SFA><SFA><FILEPATH>n:\wpi\cs 502 os\z502 ws\</FILEPATH><FILENAME>z502.c</FILENAME><LINE>1511</LINE><COLUMN>7</COLUMN></SFA><SFA><FILEPATH>n:\wpi\cs 502 os\z502 ws\</FILEPATH><FILENAME>z502.c</FILENAME><LINE>1512</LINE><COLUMN>7</COLUMN></SFA><SFA><FILEPATH>n:\wpi\cs 502 os\z502 ws\</FILEPATH><FILENAME>z502.c</FILENAME><LINE>1513</LINE><COLUMN>7</COLUMN></SFA><SFA><FILEPATH>n:\wpi\cs 502 os\z502 ws\</FILEPATH><FILENAME>z502.c</FILENAME><LINE>1514</LINE><COLUMN>7</COLUMN></SFA><SFA><FILEPATH>n:\wpi\cs 502 os\z502 ws\</FILEPATH><FILENAME>z502.c</FILENAME><LINE>1515</LINE><COLUMN>8</COLUMN></SFA><SFA><FILEPATH>n:\wpi\cs 502 os\z502 ws\</FILEPATH><FILENAME>z502.c</FILENAME><LINE>1516</LINE><COLUMN>6</COLUMN></SFA><SFA><FILEPATH>n:\wpi\cs 502 os\z502 ws\</FILEPATH><FILENAME>z502.c</FILENAME><LINE>1518</LINE><COLUMN>14</COLUMN></SFA><SFA><FILEPATH>n:\wpi\cs 502 os\z502 ws\</FILEPATH><FILENAME>z502.c</FILENAME><LINE>1519</LINE><COLUMN>8</COLUMN><KEYEVENT><ID>1</ID><KIND>branch</KIND><IMPORTANCE>Full</IMPORTANCE><MESSAGE>Enter this loop, (assume '1')</MESSAGE></KEYEVENT></SFA><SFA><FILEPATH>n:\wpi\cs 502 os\z502 ws\</FILEPATH><FILENAME>z502.c</FILENAME><LINE>1520</LINE><COLUMN>18</COLUMN></SFA><SFA><FILEPATH>n:\wpi\cs 502 os\z502 ws\</FILEPATH><FILENAME>z502.c</FILENAME><LINE>1522</LINE><COLUMN>4</COLUMN><KEYEVENT><ID>2</ID><KIND>branch</KIND><IMPORTANCE>Full</IMPORTANCE><MESSAGE>Skip this loop, (assume '&lt;branch condition&gt;' is false)</MESSAGE></KEYEVENT></SFA><SFA><FILEPATH>n:\wpi\cs 502 os\z502 ws\</FILEPATH><FILENAME>z502.c</FILENAME><LINE>1537</LINE><COLUMN>9</COLUMN></SFA><SFA><FILEPATH>n:\wpi\cs 502 os\z502 ws\</FILEPATH><FILENAME>z502.c</FILENAME><LINE>1538</LINE><COLUMN>27</COLUMN></SFA><SFA><FILEPATH>n:\wpi\cs 502 os\z502 ws\</FILEPATH><FILENAME>z502.c</FILENAME><LINE>1539</LINE><COLUMN>21</COLUMN></SFA><SFA><FILEPATH>n:\wpi\cs 502 os\z502 ws\</FILEPATH><FILENAME>z502.c</FILENAME><LINE>1541</LINE><COLUMN>18</COLUMN></SFA><SFA><FILEPATH>n:\wpi\cs 502 os\z502 ws\</FILEPATH><FILENAME>z502.c</FILENAME><LINE>1548</LINE><COLUMN>4</COLUMN><KEYEVENT><ID>3</ID><KIND>branch</KIND><IMPORTANCE>Full</IMPORTANCE><MESSAGE>Skip this branch, (assume '&lt;branch condition&gt;' is false)</MESSAGE></KEYEVENT></SFA><SFA><FILEPATH>n:\wpi\cs 502 os\z502 ws\</FILEPATH><FILENAME>z502.c</FILENAME><LINE>1599</LINE><COLUMN>36</COLUMN><KEYEVENT><ID>4</ID><KIND>branch</KIND><IMPORTANCE>Full</IMPORTANCE><MESSAGE>'event_type' may equal 4 (Skip this branch)</MESSAGE></KEYEVENT></SFA><SFA><FILEPATH>n:\wpi\cs 502 os\z502 ws\</FILEPATH><FILENAME>z502.c</FILENAME><LINE>1610</LINE><COLUMN>38</COLUMN><KEYEVENT><ID>5</ID><KIND>usage</KIND><IMPORTANCE>Essential</IMPORTANCE><MESSAGE>Invalid write to 'STAT_VECTOR[(short)0][13]', (writable range is 0 to 12)</MESSAGE></KEYEVENT></SFA></PATH></DEFECT><DEFECT><SFA><FILEPATH>n:\wpi\cs 502 os\z502 ws\</FILEPATH><FILENAME>z502.c</FILENAME><LINE>1612</LINE><COLUMN>35</COLUMN></SFA><DEFECTCODE>6386</DEFECTCODE><DESCRIPTION>Buffer overrun while writing to 'STAT_VECTOR[(short)2]':  the writable size is '52' bytes, but 'event_type' bytes might be written.</DESCRIPTION><FUNCTION>HardwareInterrupt</FUNCTION><DECORATED>HardwareInterrupt</DECORATED><FUNCLINE>1509</FUNCLINE><PROBABILITY>1</PROBABILITY><RANK>4</RANK><CATEGORY><RULECATEGORY>mspft</RULECATEGORY></CATEGORY><PATH><SFA><FILEPATH>n:\wpi\cs 502 os\z502 ws\</FILEPATH><FILENAME>z502.c</FILENAME><LINE>1510</LINE><COLUMN>7</COLUMN></SFA><SFA><FILEPATH>n:\wpi\cs 502 os\z502 ws\</FILEPATH><FILENAME>z502.c</FILENAME><LINE>1511</LINE><COLUMN>7</COLUMN></SFA><SFA><FILEPATH>n:\wpi\cs 502 os\z502 ws\</FILEPATH><FILENAME>z502.c</FILENAME><LINE>1512</LINE><COLUMN>7</COLUMN></SFA><SFA><FILEPATH>n:\wpi\cs 502 os\z502 ws\</FILEPATH><FILENAME>z502.c</FILENAME><LINE>1513</LINE><COLUMN>7</COLUMN></SFA><SFA><FILEPATH>n:\wpi\cs 502 os\z502 ws\</FILEPATH><FILENAME>z502.c</FILENAME><LINE>1514</LINE><COLUMN>7</COLUMN></SFA><SFA><FILEPATH>n:\wpi\cs 502 os\z502 ws\</FILEPATH><FILENAME>z502.c</FILENAME><LINE>1515</LINE><COLUMN>8</COLUMN></SFA><SFA><FILEPATH>n:\wpi\cs 502 os\z502 ws\</FILEPATH><FILENAME>z502.c</FILENAME><LINE>1516</LINE><COLUMN>6</COLUMN></SFA><SFA><FILEPATH>n:\wpi\cs 502 os\z502 ws\</FILEPATH><FILENAME>z502.c</FILENAME><LINE>1518</LINE><COLUMN>14</COLUMN></SFA><SFA><FILEPATH>n:\wpi\cs 502 os\z502 ws\</FILEPATH><FILENAME>z502.c</FILENAME><LINE>1519</LINE><COLUMN>8</COLUMN><KEYEVENT><ID>1</ID><KIND>branch</KIND><IMPORTANCE>Full</IMPORTANCE><MESSAGE>Enter this loop, (assume '1')</MESSAGE></KEYEVENT></SFA><SFA><FILEPATH>n:\wpi\cs 502 os\z502 ws\</FILEPATH><FILENAME>z502.c</FILENAME><LINE>1520</LINE><COLUMN>18</COLUMN></SFA><SFA><FILEPATH>n:\wpi\cs 502 os\z502 ws\</FILEPATH><FILENAME>z502.c</FILENAME><LINE>1522</LINE><COLUMN>4</COLUMN><KEYEVENT><ID>2</ID><KIND>branch</KIND><IMPORTANCE>Full</IMPORTANCE><MESSAGE>Skip this loop, (assume '&lt;branch condition&gt;' is false)</MESSAGE></KEYEVENT></SFA><SFA><FILEPATH>n:\wpi\cs 502 os\z502 ws\</FILEPATH><FILENAME>z502.c</FILENAME><LINE>1537</LINE><COLUMN>9</COLUMN></SFA><SFA><FILEPATH>n:\wpi\cs 502 os\z502 ws\</FILEPATH><FILENAME>z502.c</FILENAME><LINE>1538</LINE><COLUMN>27</COLUMN></SFA><SFA><FILEPATH>n:\wpi\cs 502 os\z502 ws\</FILEPATH><FILENAME>z502.c</FILENAME><LINE>1539</LINE><COLUMN>21</COLUMN></SFA><SFA><FILEPATH>n:\wpi\cs 502 os\z502 ws\</FILEPATH><FILENAME>z502.c</FILENAME><LINE>1541</LINE><COLUMN>18</COLUMN></SFA><SFA><FILEPATH>n:\wpi\cs 502 os\z502 ws\</FILEPATH><FILENAME>z502.c</FILENAME><LINE>1548</LINE><COLUMN>4</COLUMN><KEYEVENT><ID>3</ID><KIND>branch</KIND><IMPORTANCE>Full</IMPORTANCE><MESSAGE>Skip this branch, (assume '&lt;branch condition&gt;' is false)</MESSAGE></KEYEVENT></SFA><SFA><FILEPATH>n:\wpi\cs 502 os\z502 ws\</FILEPATH><FILENAME>z502.c</FILENAME><LINE>1599</LINE><COLUMN>36</COLUMN><KEYEVENT><ID>4</ID><KIND>branch</KIND><IMPORTANCE>Full</IMPORTANCE><MESSAGE>'event_type' may equal 4 (Skip this branch)</MESSAGE></KEYEVENT></SFA><SFA><FILEPATH>n:\wpi\cs 502 os\z502 ws\</FILEPATH><FILENAME>z502.c</FILENAME><LINE>1610</LINE><COLUMN>38</COLUMN></SFA><SFA><FILEPATH>n:\wpi\cs 502 os\z502 ws\</FILEPATH><FILENAME>z502.c</FILENAME><LINE>1611</LINE><COLUMN>37</COLUMN></SFA><SFA><FILEPATH>n:\wpi\cs 502 os\z502 ws\</FILEPATH><FILENAME>z502.c</FILENAME><LINE>1612</LINE><COLUMN>35</COLUMN><KEYEVENT><ID>5</ID><KIND>usage</KIND><IMPORTANCE>Essential</IMPORTANCE><MESSAGE>Invalid write to 'STAT_VECTOR[(short)2][13]', (writable range is 0 to 12)</MESSAGE></KEYEVENT></SFA></PATH></DEFECT><DEFECT><SFA><FILEPATH>n:\wpi\cs 502 os\z502 ws\</FILEPATH><FILENAME>z502.c</FILENAME><LINE>1788</LINE><COLUMN>11</COLUMN></SFA><DEFECTCODE>6011</DEFECTCODE><DESCRIPTION>Dereferencing NULL pointer 'ep'. </DESCRIPTION><FUNCTION>AddEventToInterruptQueue</FUNCTION><DECORATED>AddEventToInterruptQueue</DECORATED><FUNCLINE>1760</FUNCLINE><PROBABILITY>1</PROBABILITY><RANK>4</RANK><CATEGORY><RULECATEGORY>mspft</RULECATEGORY></CATEGORY><PATH><SFA><FILEPATH>n:\wpi\cs 502 os\z502 ws\</FILEPATH><FILENAME>z502.c</FILENAME><LINE>1762</LINE><COLUMN>8</COLUMN></SFA><SFA><FILEPATH>n:\wpi\cs 502 os\z502 ws\</FILEPATH><FILENAME>z502.c</FILENAME><LINE>1763</LINE><COLUMN>8</COLUMN></SFA><SFA><FILEPATH>n:\wpi\cs 502 os\z502 ws\</FILEPATH><FILENAME>z502.c</FILENAME><LINE>1764</LINE><COLUMN>8</COLUMN></SFA><SFA><FILEPATH>n:\wpi\cs 502 os\z502 ws\</FILEPATH><FILENAME>z502.c</FILENAME><LINE>1765</LINE><COLUMN>7</COLUMN></SFA><SFA><FILEPATH>n:\wpi\cs 502 os\z502 ws\</FILEPATH><FILENAME>z502.c</FILENAME><LINE>1767</LINE><COLUMN>19</COLUMN></SFA><SFA><FILEPATH>n:\wpi\cs 502 os\z502 ws\</FILEPATH><FILENAME>z502.c</FILENAME><LINE>1777</LINE><COLUMN>20</COLUMN></SFA><SFA><FILEPATH>n:\wpi\cs 502 os\z502 ws\</FILEPATH><FILENAME>z502.c</FILENAME><LINE>1781</LINE><COLUMN>4</COLUMN><KEYEVENT><ID>1</ID><KIND>declaration</KIND><IMPORTANCE>Essential</IMPORTANCE><MESSAGE>'ep' may be NULL</MESSAGE></KEYEVENT></SFA><SFA><FILEPATH>n:\wpi\cs 502 os\z502 ws\</FILEPATH><FILENAME>z502.c</FILENAME><LINE>1782</LINE><COLUMN>8</COLUMN><KEYEVENT><ID>2</ID><KIND>branch</KIND><IMPORTANCE>Full</IMPORTANCE><MESSAGE>Enter this branch, (assume 'ep==(((void *)0))')</MESSAGE></KEYEVENT></SFA><SFA><FILEPATH>n:\wpi\cs 502 os\z502 ws\</FILEPATH><FILENAME>z502.c</FILENAME><LINE>1783</LINE><COLUMN>8</COLUMN></SFA><SFA><FILEPATH>n:\wpi\cs 502 os\z502 ws\</FILEPATH><FILENAME>z502.c</FILENAME><LINE>1784</LINE><COLUMN>23</COLUMN></SFA><SFA><FILEPATH>n:\wpi\cs 502 os\z502 ws\</FILEPATH><FILENAME>z502.c</FILENAME><LINE>1786</LINE><COLUMN>8</COLUMN></SFA><SFA><FILEPATH>n:\wpi\cs 502 os\z502 ws\</FILEPATH><FILENAME>z502.c</FILENAME><LINE>1788</LINE><COLUMN>11</COLUMN><KEYEVENT><ID>3</ID><KIND>usage</KIND><IMPORTANCE>Essential</IMPORTANCE><MESSAGE>'ep' is dereferenced, but may still be NULL</MESSAGE></KEYEVENT></SFA></PATH></DEFECT><DEFECT><SFA><FILEPATH>n:\wpi\cs 502 os\z502 ws\</FILEPATH><FILENAME>z502.c</FILENAME><LINE>2058</LINE><COLUMN>7</COLUMN></SFA><DEFECTCODE>6340</DEFECTCODE><DESCRIPTION>Mismatch on sign: 'unsigned int' passed as _Param_(2) when some signed type is required in call to 'printf'.</DESCRIPTION><FUNCTION>PrintRingBuffer</FUNCTION><DECORATED>PrintRingBuffer</DECORATED><FUNCLINE>2049</FUNCLINE><PATH/></DEFECT><DEFECT><SFA><FILEPATH>n:\wpi\cs 502 os\z502 ws\</FILEPATH><FILENAME>z502.c</FILENAME><LINE>2159</LINE><COLUMN>19</COLUMN></SFA><DEFECTCODE>6011</DEFECTCODE><DESCRIPTION>Dereferencing NULL pointer 'ssp'. </DESCRIPTION><FUNCTION>CreateSectorStruct</FUNCTION><DECORATED>CreateSectorStruct</DECORATED><FUNCLINE>2150</FUNCLINE><PROBABILITY>1</PROBABILITY><RANK>4</RANK><CATEGORY><RULECATEGORY>mspft</RULECATEGORY></CATEGORY><PATH><SFA><FILEPATH>n:\wpi\cs 502 os\z502 ws\</FILEPATH><FILENAME>z502.c</FILENAME><LINE>2151</LINE><COLUMN>9</COLUMN></SFA><SFA><FILEPATH>n:\wpi\cs 502 os\z502 ws\</FILEPATH><FILENAME>z502.c</FILENAME><LINE>2153</LINE><COLUMN>5</COLUMN><KEYEVENT><ID>1</ID><KIND>declaration</KIND><IMPORTANCE>Essential</IMPORTANCE><MESSAGE>'ssp' may be NULL</MESSAGE></KEYEVENT></SFA><SFA><FILEPATH>n:\wpi\cs 502 os\z502 ws\</FILEPATH><FILENAME>z502.c</FILENAME><LINE>2154</LINE><COLUMN>9</COLUMN><KEYEVENT><ID>2</ID><KIND>branch</KIND><IMPORTANCE>Full</IMPORTANCE><MESSAGE>Enter this branch, (assume 'ssp==(((void *)0))')</MESSAGE></KEYEVENT></SFA><SFA><FILEPATH>n:\wpi\cs 502 os\z502 ws\</FILEPATH><FILENAME>z502.c</FILENAME><LINE>2155</LINE><COLUMN>8</COLUMN></SFA><SFA><FILEPATH>n:\wpi\cs 502 os\z502 ws\</FILEPATH><FILENAME>z502.c</FILENAME><LINE>2156</LINE><COLUMN>8</COLUMN></SFA><SFA><FILEPATH>n:\wpi\cs 502 os\z502 ws\</FILEPATH><FILENAME>z502.c</FILENAME><LINE>2157</LINE><COLUMN>23</COLUMN></SFA><SFA><FILEPATH>n:\wpi\cs 502 os\z502 ws\</FILEPATH><FILENAME>z502.c</FILENAME><LINE>2159</LINE><COLUMN>19</COLUMN><KEYEVENT><ID>3</ID><KIND>usage</KIND><IMPORTANCE>Essential</IMPORTANCE><MESSAGE>'ssp' is dereferenced, but may still be NULL</MESSAGE></KEYEVENT></SFA></PATH></DEFECT><DEFECT><SFA><FILEPATH>n:\wpi\cs 502 os\z502 ws\</FILEPATH><FILENAME>z502.c</FILENAME><LINE>2223</LINE><COLUMN>10</COLUMN></SFA><DEFECTCODE>6340</DEFECTCODE><DESCRIPTION>Mismatch on sign: 'unsigned int' passed as _Param_(6) when some signed type is required in call to 'printf'.</DESCRIPTION><FUNCTION>PrintThreadTable</FUNCTION><DECORATED>PrintThreadTable</DECORATED><FUNCLINE>2216</FUNCLINE><PATH/></DEFECT><DEFECT><SFA><FILEPATH>n:\wpi\cs 502 os\z502 ws\</FILEPATH><FILENAME>z502.c</FILENAME><LINE>2223</LINE><COLUMN>10</COLUMN></SFA><DEFECTCODE>6340</DEFECTCODE><DESCRIPTION>Mismatch on sign: 'unsigned int' passed as _Param_(7) when some signed type is required in call to 'printf'.</DESCRIPTION><FUNCTION>PrintThreadTable</FUNCTION><DECORATED>PrintThreadTable</DECORATED><FUNCLINE>2216</FUNCLINE><PATH/></DEFECT><DEFECT><SFA><FILEPATH>n:\wpi\cs 502 os\z502 ws\</FILEPATH><FILENAME>z502.c</FILENAME><LINE>2266</LINE><COLUMN>36</COLUMN></SFA><DEFECTCODE>6386</DEFECTCODE><DESCRIPTION>Buffer overrun while writing to 'ThreadTable':  the writable size is '840' bytes, but '-28' bytes might be written.</DESCRIPTION><FUNCTION>Z502CreateUserThread</FUNCTION><DECORATED>Z502CreateUserThread</DECORATED><FUNCLINE>2244</FUNCLINE><PROBABILITY>1</PROBABILITY><RANK>4</RANK><CATEGORY><RULECATEGORY>mspft</RULECATEGORY></CATEGORY><PATH><SFA><FILEPATH>n:\wpi\cs 502 os\z502 ws\</FILEPATH><FILENAME>z502.c</FILENAME><LINE>2245</LINE><COLUMN>5</COLUMN><KEYEVENT><ID>1</ID><KIND>declaration</KIND><IMPORTANCE>Essential</IMPORTANCE><MESSAGE>'ourLocalID' is equal to -1</MESSAGE></KEYEVENT></SFA><SFA><FILEPATH>n:\wpi\cs 502 os\z502 ws\</FILEPATH><FILENAME>z502.c</FILENAME><LINE>2246</LINE><COLUMN>5</COLUMN></SFA><SFA><FILEPATH>n:\wpi\cs 502 os\z502 ws\</FILEPATH><FILENAME>z502.c</FILENAME><LINE>2248</LINE><COLUMN>21</COLUMN></SFA><SFA><FILEPATH>n:\wpi\cs 502 os\z502 ws\</FILEPATH><FILENAME>z502.c</FILENAME><LINE>2250</LINE><COLUMN>8</COLUMN></SFA><SFA><FILEPATH>n:\wpi\cs 502 os\z502 ws\</FILEPATH><FILENAME>z502.c</FILENAME><LINE>2252</LINE><COLUMN>8</COLUMN></SFA><SFA><FILEPATH>n:\wpi\cs 502 os\z502 ws\</FILEPATH><FILENAME>z502.c</FILENAME><LINE>2252</LINE><COLUMN>15</COLUMN><KEYEVENT><ID>2</ID><KIND>branch</KIND><IMPORTANCE>Full</IMPORTANCE><MESSAGE>Enter this loop, (assume 'i&lt;25+5')</MESSAGE></KEYEVENT></SFA><SFA><FILEPATH>n:\wpi\cs 502 os\z502 ws\</FILEPATH><FILENAME>z502.c</FILENAME><LINE>2253</LINE><COLUMN>32</COLUMN><KEYEVENT><ID>3</ID><KIND>branch</KIND><IMPORTANCE>Full</IMPORTANCE><MESSAGE>Skip this branch, (assume 'ThreadTable[i].OurLocalID==-1' is false)</MESSAGE></KEYEVENT></SFA><SFA><FILEPATH>n:\wpi\cs 502 os\z502 ws\</FILEPATH><FILENAME>z502.c</FILENAME><LINE>2252</LINE><COLUMN>41</COLUMN></SFA><SFA><FILEPATH>n:\wpi\cs 502 os\z502 ws\</FILEPATH><FILENAME>z502.c</FILENAME><LINE>2252</LINE><COLUMN>15</COLUMN><KEYEVENT><ID>4</ID><KIND>branch</KIND><IMPORTANCE>Full</IMPORTANCE><MESSAGE>Enter this loop, (assume 'i&lt;25+5')</MESSAGE></KEYEVENT></SFA><SFA><FILEPATH>n:\wpi\cs 502 os\z502 ws\</FILEPATH><FILENAME>z502.c</FILENAME><LINE>2253</LINE><COLUMN>32</COLUMN><KEYEVENT><ID>5</ID><KIND>branch</KIND><IMPORTANCE>Full</IMPORTANCE><MESSAGE>Skip this branch, (assume 'ThreadTable[i].OurLocalID==-1' is false)</MESSAGE></KEYEVENT></SFA><SFA><FILEPATH>n:\wpi\cs 502 os\z502 ws\</FILEPATH><FILENAME>z502.c</FILENAME><LINE>2252</LINE><COLUMN>41</COLUMN></SFA><SFA><FILEPATH>n:\wpi\cs 502 os\z502 ws\</FILEPATH><FILENAME>z502.c</FILENAME><LINE>2252</LINE><COLUMN>15</COLUMN><KEYEVENT><ID>6</ID><KIND>branch</KIND><IMPORTANCE>Full</IMPORTANCE><MESSAGE>Continue this loop, (assume 'i&lt;25+5')</MESSAGE></KEYEVENT></SFA><SFA><FILEPATH>n:\wpi\cs 502 os\z502 ws\</FILEPATH><FILENAME>z502.c</FILENAME><LINE>2261</LINE><COLUMN>16</COLUMN><KEYEVENT><ID>7</ID><KIND>branch</KIND><IMPORTANCE>Full</IMPORTANCE><MESSAGE>Enter this branch, (assume 'ourLocalID==-1')</MESSAGE></KEYEVENT></SFA><SFA><FILEPATH>n:\wpi\cs 502 os\z502 ws\</FILEPATH><FILENAME>z502.c</FILENAME><LINE>2262</LINE><COLUMN>8</COLUMN></SFA><SFA><FILEPATH>n:\wpi\cs 502 os\z502 ws\</FILEPATH><FILENAME>z502.c</FILENAME><LINE>2263</LINE><COLUMN>23</COLUMN></SFA><SFA><FILEPATH>n:\wpi\cs 502 os\z502 ws\</FILEPATH><FILENAME>z502.c</FILENAME><LINE>2266</LINE><COLUMN>36</COLUMN><KEYEVENT><ID>8</ID><KIND>usage</KIND><IMPORTANCE>Essential</IMPORTANCE><MESSAGE>Invalid write to 'ThreadTable[-1]', (writable range is 0 to 29)</MESSAGE></KEYEVENT></SFA></PATH></DEFECT><DEFECT><SFA><FILEPATH>n:\wpi\cs 502 os\z502 ws\</FILEPATH><FILENAME>z502.c</FILENAME><LINE>2324</LINE><COLUMN>38</COLUMN></SFA><DEFECTCODE>6386</DEFECTCODE><DESCRIPTION>Buffer overrun while writing to 'ThreadTable':  the writable size is '840' bytes, but '-28' bytes might be written.</DESCRIPTION><FUNCTION>Z502PrepareProcessForExecution</FUNCTION><DECORATED>Z502PrepareProcessForExecution</DECORATED><FUNCLINE>2301</FUNCLINE><PROBABILITY>1</PROBABILITY><RANK>4</RANK><CATEGORY><RULECATEGORY>mspft</RULECATEGORY></CATEGORY><PATH><SFA><FILEPATH>n:\wpi\cs 502 os\z502 ws\</FILEPATH><FILENAME>z502.c</FILENAME><LINE>2302</LINE><COLUMN>5</COLUMN></SFA><SFA><FILEPATH>n:\wpi\cs 502 os\z502 ws\</FILEPATH><FILENAME>z502.c</FILENAME><LINE>2303</LINE><COLUMN>5</COLUMN><KEYEVENT><ID>1</ID><KIND>declaration</KIND><IMPORTANCE>Essential</IMPORTANCE><MESSAGE>'ourLocalID' is equal to -1</MESSAGE></KEYEVENT></SFA><SFA><FILEPATH>n:\wpi\cs 502 os\z502 ws\</FILEPATH><FILENAME>z502.c</FILENAME><LINE>2304</LINE><COLUMN>5</COLUMN></SFA><SFA><FILEPATH>n:\wpi\cs 502 os\z502 ws\</FILEPATH><FILENAME>z502.c</FILENAME><LINE>2305</LINE><COLUMN>8</COLUMN></SFA><SFA><FILEPATH>n:\wpi\cs 502 os\z502 ws\</FILEPATH><FILENAME>z502.c</FILENAME><LINE>2306</LINE><COLUMN>7</COLUMN></SFA><SFA><FILEPATH>n:\wpi\cs 502 os\z502 ws\</FILEPATH><FILENAME>z502.c</FILENAME><LINE>2308</LINE><COLUMN>6</COLUMN></SFA><SFA><FILEPATH>n:\wpi\cs 502 os\z502 ws\</FILEPATH><FILENAME>z502.c</FILENAME><LINE>2309</LINE><COLUMN>8</COLUMN></SFA><SFA><FILEPATH>n:\wpi\cs 502 os\z502 ws\</FILEPATH><FILENAME>z502.c</FILENAME><LINE>2310</LINE><COLUMN>17</COLUMN></SFA><SFA><FILEPATH>n:\wpi\cs 502 os\z502 ws\</FILEPATH><FILENAME>z502.c</FILENAME><LINE>2312</LINE><COLUMN>8</COLUMN></SFA><SFA><FILEPATH>n:\wpi\cs 502 os\z502 ws\</FILEPATH><FILENAME>z502.c</FILENAME><LINE>2312</LINE><COLUMN>15</COLUMN><KEYEVENT><ID>2</ID><KIND>branch</KIND><IMPORTANCE>Full</IMPORTANCE><MESSAGE>Enter this loop, (assume 'i&lt;25+5')</MESSAGE></KEYEVENT></SFA><SFA><FILEPATH>n:\wpi\cs 502 os\z502 ws\</FILEPATH><FILENAME>z502.c</FILENAME><LINE>2313</LINE><COLUMN>30</COLUMN><KEYEVENT><ID>3</ID><KIND>branch</KIND><IMPORTANCE>Full</IMPORTANCE><MESSAGE>Skip this branch, (assume 'ThreadTable[i].ThreadID==myTid' is false)</MESSAGE></KEYEVENT></SFA><SFA><FILEPATH>n:\wpi\cs 502 os\z502 ws\</FILEPATH><FILENAME>z502.c</FILENAME><LINE>2312</LINE><COLUMN>41</COLUMN></SFA><SFA><FILEPATH>n:\wpi\cs 502 os\z502 ws\</FILEPATH><FILENAME>z502.c</FILENAME><LINE>2312</LINE><COLUMN>15</COLUMN><KEYEVENT><ID>4</ID><KIND>branch</KIND><IMPORTANCE>Full</IMPORTANCE><MESSAGE>Enter this loop, (assume 'i&lt;25+5')</MESSAGE></KEYEVENT></SFA><SFA><FILEPATH>n:\wpi\cs 502 os\z502 ws\</FILEPATH><FILENAME>z502.c</FILENAME><LINE>2313</LINE><COLUMN>30</COLUMN><KEYEVENT><ID>5</ID><KIND>branch</KIND><IMPORTANCE>Full</IMPORTANCE><MESSAGE>Skip this branch, (assume 'ThreadTable[i].ThreadID==myTid' is false)</MESSAGE></KEYEVENT></SFA><SFA><FILEPATH>n:\wpi\cs 502 os\z502 ws\</FILEPATH><FILENAME>z502.c</FILENAME><LINE>2312</LINE><COLUMN>41</COLUMN></SFA><SFA><FILEPATH>n:\wpi\cs 502 os\z502 ws\</FILEPATH><FILENAME>z502.c</FILENAME><LINE>2312</LINE><COLUMN>15</COLUMN><KEYEVENT><ID>6</ID><KIND>branch</KIND><IMPORTANCE>Full</IMPORTANCE><MESSAGE>Continue this loop, (assume 'i&lt;25+5')</MESSAGE></KEYEVENT></SFA><SFA><FILEPATH>n:\wpi\cs 502 os\z502 ws\</FILEPATH><FILENAME>z502.c</FILENAME><LINE>2318</LINE><COLUMN>16</COLUMN><KEYEVENT><ID>7</ID><KIND>branch</KIND><IMPORTANCE>Full</IMPORTANCE><MESSAGE>Enter this branch, (assume 'ourLocalID==-1')</MESSAGE></KEYEVENT></SFA><SFA><FILEPATH>n:\wpi\cs 502 os\z502 ws\</FILEPATH><FILENAME>z502.c</FILENAME><LINE>2319</LINE><COLUMN>8</COLUMN></SFA><SFA><FILEPATH>n:\wpi\cs 502 os\z502 ws\</FILEPATH><FILENAME>z502.c</FILENAME><LINE>2320</LINE><COLUMN>23</COLUMN></SFA><SFA><FILEPATH>n:\wpi\cs 502 os\z502 ws\</FILEPATH><FILENAME>z502.c</FILENAME><LINE>2324</LINE><COLUMN>38</COLUMN><KEYEVENT><ID>8</ID><KIND>usage</KIND><IMPORTANCE>Essential</IMPORTANCE><MESSAGE>Invalid write to 'ThreadTable[-1]', (writable range is 0 to 29)</MESSAGE></KEYEVENT></SFA></PATH></DEFECT><DEFECT><SFA><FILEPATH>n:\wpi\cs 502 os\z502 ws\</FILEPATH><FILENAME>z502.c</FILENAME><LINE>2333</LINE><COLUMN>45</COLUMN></SFA><DEFECTCODE>6385</DEFECTCODE><DESCRIPTION>Reading invalid data from 'ThreadTable':  the readable size is '840' bytes, but '-28' bytes may be read.</DESCRIPTION><FUNCTION>Z502PrepareProcessForExecution</FUNCTION><DECORATED>Z502PrepareProcessForExecution</DECORATED><FUNCLINE>2301</FUNCLINE><PROBABILITY>1</PROBABILITY><RANK>4</RANK><CATEGORY><RULECATEGORY>mspft</RULECATEGORY></CATEGORY><PATH><SFA><FILEPATH>n:\wpi\cs 502 os\z502 ws\</FILEPATH><FILENAME>z502.c</FILENAME><LINE>2302</LINE><COLUMN>5</COLUMN></SFA><SFA><FILEPATH>n:\wpi\cs 502 os\z502 ws\</FILEPATH><FILENAME>z502.c</FILENAME><LINE>2303</LINE><COLUMN>5</COLUMN><KEYEVENT><ID>1</ID><KIND>declaration</KIND><IMPORTANCE>Essential</IMPORTANCE><MESSAGE>'ourLocalID' is equal to -1</MESSAGE></KEYEVENT></SFA><SFA><FILEPATH>n:\wpi\cs 502 os\z502 ws\</FILEPATH><FILENAME>z502.c</FILENAME><LINE>2304</LINE><COLUMN>5</COLUMN></SFA><SFA><FILEPATH>n:\wpi\cs 502 os\z502 ws\</FILEPATH><FILENAME>z502.c</FILENAME><LINE>2305</LINE><COLUMN>8</COLUMN></SFA><SFA><FILEPATH>n:\wpi\cs 502 os\z502 ws\</FILEPATH><FILENAME>z502.c</FILENAME><LINE>2306</LINE><COLUMN>7</COLUMN></SFA><SFA><FILEPATH>n:\wpi\cs 502 os\z502 ws\</FILEPATH><FILENAME>z502.c</FILENAME><LINE>2308</LINE><COLUMN>6</COLUMN></SFA><SFA><FILEPATH>n:\wpi\cs 502 os\z502 ws\</FILEPATH><FILENAME>z502.c</FILENAME><LINE>2309</LINE><COLUMN>8</COLUMN></SFA><SFA><FILEPATH>n:\wpi\cs 502 os\z502 ws\</FILEPATH><FILENAME>z502.c</FILENAME><LINE>2310</LINE><COLUMN>17</COLUMN></SFA><SFA><FILEPATH>n:\wpi\cs 502 os\z502 ws\</FILEPATH><FILENAME>z502.c</FILENAME><LINE>2312</LINE><COLUMN>8</COLUMN></SFA><SFA><FILEPATH>n:\wpi\cs 502 os\z502 ws\</FILEPATH><FILENAME>z502.c</FILENAME><LINE>2312</LINE><COLUMN>15</COLUMN><KEYEVENT><ID>2</ID><KIND>branch</KIND><IMPORTANCE>Full</IMPORTANCE><MESSAGE>Enter this loop, (assume 'i&lt;25+5')</MESSAGE></KEYEVENT></SFA><SFA><FILEPATH>n:\wpi\cs 502 os\z502 ws\</FILEPATH><FILENAME>z502.c</FILENAME><LINE>2313</LINE><COLUMN>30</COLUMN><KEYEVENT><ID>3</ID><KIND>branch</KIND><IMPORTANCE>Full</IMPORTANCE><MESSAGE>Skip this branch, (assume 'ThreadTable[i].ThreadID==myTid' is false)</MESSAGE></KEYEVENT></SFA><SFA><FILEPATH>n:\wpi\cs 502 os\z502 ws\</FILEPATH><FILENAME>z502.c</FILENAME><LINE>2312</LINE><COLUMN>41</COLUMN></SFA><SFA><FILEPATH>n:\wpi\cs 502 os\z502 ws\</FILEPATH><FILENAME>z502.c</FILENAME><LINE>2312</LINE><COLUMN>15</COLUMN><KEYEVENT><ID>4</ID><KIND>branch</KIND><IMPORTANCE>Full</IMPORTANCE><MESSAGE>Enter this loop, (assume 'i&lt;25+5')</MESSAGE></KEYEVENT></SFA><SFA><FILEPATH>n:\wpi\cs 502 os\z502 ws\</FILEPATH><FILENAME>z502.c</FILENAME><LINE>2313</LINE><COLUMN>30</COLUMN><KEYEVENT><ID>5</ID><KIND>branch</KIND><IMPORTANCE>Full</IMPORTANCE><MESSAGE>Skip this branch, (assume 'ThreadTable[i].ThreadID==myTid' is false)</MESSAGE></KEYEVENT></SFA><SFA><FILEPATH>n:\wpi\cs 502 os\z502 ws\</FILEPATH><FILENAME>z502.c</FILENAME><LINE>2312</LINE><COLUMN>41</COLUMN></SFA><SFA><FILEPATH>n:\wpi\cs 502 os\z502 ws\</FILEPATH><FILENAME>z502.c</FILENAME><LINE>2312</LINE><COLUMN>15</COLUMN><KEYEVENT><ID>6</ID><KIND>branch</KIND><IMPORTANCE>Full</IMPORTANCE><MESSAGE>Continue this loop, (assume 'i&lt;25+5')</MESSAGE></KEYEVENT></SFA><SFA><FILEPATH>n:\wpi\cs 502 os\z502 ws\</FILEPATH><FILENAME>z502.c</FILENAME><LINE>2318</LINE><COLUMN>16</COLUMN><KEYEVENT><ID>7</ID><KIND>branch</KIND><IMPORTANCE>Full</IMPORTANCE><MESSAGE>Enter this branch, (assume 'ourLocalID==-1')</MESSAGE></KEYEVENT></SFA><SFA><FILEPATH>n:\wpi\cs 502 os\z502 ws\</FILEPATH><FILENAME>z502.c</FILENAME><LINE>2319</LINE><COLUMN>8</COLUMN></SFA><SFA><FILEPATH>n:\wpi\cs 502 os\z502 ws\</FILEPATH><FILENAME>z502.c</FILENAME><LINE>2320</LINE><COLUMN>23</COLUMN></SFA><SFA><FILEPATH>n:\wpi\cs 502 os\z502 ws\</FILEPATH><FILENAME>z502.c</FILENAME><LINE>2324</LINE><COLUMN>38</COLUMN></SFA><SFA><FILEPATH>n:\wpi\cs 502 os\z502 ws\</FILEPATH><FILENAME>z502.c</FILENAME><LINE>2327</LINE><COLUMN>16</COLUMN></SFA><SFA><FILEPATH>n:\wpi\cs 502 os\z502 ws\</FILEPATH><FILENAME>z502.c</FILENAME><LINE>2328</LINE><COLUMN>35</COLUMN></SFA><SFA><FILEPATH>n:\wpi\cs 502 os\z502 ws\</FILEPATH><FILENAME>z502.c</FILENAME><LINE>2329</LINE><COLUMN>11</COLUMN></SFA><SFA><FILEPATH>n:\wpi\cs 502 os\z502 ws\</FILEPATH><FILENAME>z502.c</FILENAME><LINE>2330</LINE><COLUMN>31</COLUMN></SFA><SFA><FILEPATH>n:\wpi\cs 502 os\z502 ws\</FILEPATH><FILENAME>z502.c</FILENAME><LINE>2331</LINE><COLUMN>12</COLUMN></SFA><SFA><FILEPATH>n:\wpi\cs 502 os\z502 ws\</FILEPATH><FILENAME>z502.c</FILENAME><LINE>2333</LINE><COLUMN>45</COLUMN><KEYEVENT><ID>8</ID><KIND>usage</KIND><IMPORTANCE>Essential</IMPORTANCE><MESSAGE>Invalid read from 'ThreadTable[-1]', (readable range is 0 to 29)</MESSAGE></KEYEVENT></SFA></PATH></DEFECT><DEFECT><SFA><FILEPATH>n:\wpi\cs 502 os\z502 ws\</FILEPATH><FILENAME>z502.c</FILENAME><LINE>2372</LINE><COLUMN>33</COLUMN></SFA><DEFECTCODE>6386</DEFECTCODE><DESCRIPTION>Buffer overrun while writing to 'ThreadTable':  the writable size is '840' bytes, but '-28' bytes might be written.</DESCRIPTION><FUNCTION>AssociateContextWithProcess</FUNCTION><DECORATED>AssociateContextWithProcess</DECORATED><FUNCLINE>2356</FUNCLINE><PROBABILITY>1</PROBABILITY><RANK>4</RANK><CATEGORY><RULECATEGORY>mspft</RULECATEGORY></CATEGORY><PATH><SFA><FILEPATH>n:\wpi\cs 502 os\z502 ws\</FILEPATH><FILENAME>z502.c</FILENAME><LINE>2357</LINE><COLUMN>5</COLUMN><KEYEVENT><ID>1</ID><KIND>declaration</KIND><IMPORTANCE>Essential</IMPORTANCE><MESSAGE>'ourLocalID' is equal to -1</MESSAGE></KEYEVENT></SFA><SFA><FILEPATH>n:\wpi\cs 502 os\z502 ws\</FILEPATH><FILENAME>z502.c</FILENAME><LINE>2358</LINE><COLUMN>5</COLUMN></SFA><SFA><FILEPATH>n:\wpi\cs 502 os\z502 ws\</FILEPATH><FILENAME>z502.c</FILENAME><LINE>2360</LINE><COLUMN>17</COLUMN></SFA><SFA><FILEPATH>n:\wpi\cs 502 os\z502 ws\</FILEPATH><FILENAME>z502.c</FILENAME><LINE>2362</LINE><COLUMN>8</COLUMN></SFA><SFA><FILEPATH>n:\wpi\cs 502 os\z502 ws\</FILEPATH><FILENAME>z502.c</FILENAME><LINE>2362</LINE><COLUMN>15</COLUMN><KEYEVENT><ID>2</ID><KIND>branch</KIND><IMPORTANCE>Full</IMPORTANCE><MESSAGE>Enter this loop, (assume 'i&lt;25+5')</MESSAGE></KEYEVENT></SFA><SFA><FILEPATH>n:\wpi\cs 502 os\z502 ws\</FILEPATH><FILENAME>z502.c</FILENAME><LINE>2363</LINE><COLUMN>34</COLUMN><KEYEVENT><ID>3</ID><KIND>branch</KIND><IMPORTANCE>Full</IMPORTANCE><MESSAGE>Skip this branch, (assume 'ThreadTable[i].CurrentState==2' is false)</MESSAGE></KEYEVENT></SFA><SFA><FILEPATH>n:\wpi\cs 502 os\z502 ws\</FILEPATH><FILENAME>z502.c</FILENAME><LINE>2362</LINE><COLUMN>41</COLUMN></SFA><SFA><FILEPATH>n:\wpi\cs 502 os\z502 ws\</FILEPATH><FILENAME>z502.c</FILENAME><LINE>2362</LINE><COLUMN>15</COLUMN><KEYEVENT><ID>4</ID><KIND>branch</KIND><IMPORTANCE>Full</IMPORTANCE><MESSAGE>Enter this loop, (assume 'i&lt;25+5')</MESSAGE></KEYEVENT></SFA><SFA><FILEPATH>n:\wpi\cs 502 os\z502 ws\</FILEPATH><FILENAME>z502.c</FILENAME><LINE>2363</LINE><COLUMN>34</COLUMN><KEYEVENT><ID>5</ID><KIND>branch</KIND><IMPORTANCE>Full</IMPORTANCE><MESSAGE>Skip this branch, (assume 'ThreadTable[i].CurrentState==2' is false)</MESSAGE></KEYEVENT></SFA><SFA><FILEPATH>n:\wpi\cs 502 os\z502 ws\</FILEPATH><FILENAME>z502.c</FILENAME><LINE>2362</LINE><COLUMN>41</COLUMN></SFA><SFA><FILEPATH>n:\wpi\cs 502 os\z502 ws\</FILEPATH><FILENAME>z502.c</FILENAME><LINE>2362</LINE><COLUMN>15</COLUMN><KEYEVENT><ID>6</ID><KIND>branch</KIND><IMPORTANCE>Full</IMPORTANCE><MESSAGE>Continue this loop, (assume 'i&lt;25+5')</MESSAGE></KEYEVENT></SFA><SFA><FILEPATH>n:\wpi\cs 502 os\z502 ws\</FILEPATH><FILENAME>z502.c</FILENAME><LINE>2368</LINE><COLUMN>16</COLUMN><KEYEVENT><ID>7</ID><KIND>branch</KIND><IMPORTANCE>Full</IMPORTANCE><MESSAGE>Enter this branch, (assume 'ourLocalID==-1')</MESSAGE></KEYEVENT></SFA><SFA><FILEPATH>n:\wpi\cs 502 os\z502 ws\</FILEPATH><FILENAME>z502.c</FILENAME><LINE>2369</LINE><COLUMN>8</COLUMN></SFA><SFA><FILEPATH>n:\wpi\cs 502 os\z502 ws\</FILEPATH><FILENAME>z502.c</FILENAME><LINE>2370</LINE><COLUMN>23</COLUMN></SFA><SFA><FILEPATH>n:\wpi\cs 502 os\z502 ws\</FILEPATH><FILENAME>z502.c</FILENAME><LINE>2372</LINE><COLUMN>33</COLUMN><KEYEVENT><ID>8</ID><KIND>usage</KIND><IMPORTANCE>Essential</IMPORTANCE><MESSAGE>Invalid write to 'ThreadTable[-1]', (writable range is 0 to 29)</MESSAGE></KEYEVENT></SFA></PATH></DEFECT><DEFECT><SFA><FILEPATH>n:\wpi\cs 502 os\z502 ws\</FILEPATH><FILENAME>z502.c</FILENAME><LINE>2398</LINE><COLUMN>38</COLUMN></SFA><DEFECTCODE>6386</DEFECTCODE><DESCRIPTION>Buffer overrun while writing to 'ThreadTable':  the writable size is '840' bytes, but '-28' bytes might be written.</DESCRIPTION><FUNCTION>ResumeProcessExecution</FUNCTION><DECORATED>ResumeProcessExecution</DECORATED><FUNCLINE>2383</FUNCLINE><PROBABILITY>1</PROBABILITY><RANK>4</RANK><CATEGORY><RULECATEGORY>mspft</RULECATEGORY></CATEGORY><PATH><SFA><FILEPATH>n:\wpi\cs 502 os\z502 ws\</FILEPATH><FILENAME>z502.c</FILENAME><LINE>2384</LINE><COLUMN>5</COLUMN><KEYEVENT><ID>1</ID><KIND>declaration</KIND><IMPORTANCE>Essential</IMPORTANCE><MESSAGE>'ourLocalID' is equal to -1</MESSAGE></KEYEVENT></SFA><SFA><FILEPATH>n:\wpi\cs 502 os\z502 ws\</FILEPATH><FILENAME>z502.c</FILENAME><LINE>2385</LINE><COLUMN>5</COLUMN></SFA><SFA><FILEPATH>n:\wpi\cs 502 os\z502 ws\</FILEPATH><FILENAME>z502.c</FILENAME><LINE>2387</LINE><COLUMN>8</COLUMN></SFA><SFA><FILEPATH>n:\wpi\cs 502 os\z502 ws\</FILEPATH><FILENAME>z502.c</FILENAME><LINE>2388</LINE><COLUMN>8</COLUMN></SFA><SFA><FILEPATH>n:\wpi\cs 502 os\z502 ws\</FILEPATH><FILENAME>z502.c</FILENAME><LINE>2388</LINE><COLUMN>15</COLUMN><KEYEVENT><ID>2</ID><KIND>branch</KIND><IMPORTANCE>Full</IMPORTANCE><MESSAGE>Enter this loop, (assume 'i&lt;25+5')</MESSAGE></KEYEVENT></SFA><SFA><FILEPATH>n:\wpi\cs 502 os\z502 ws\</FILEPATH><FILENAME>z502.c</FILENAME><LINE>2389</LINE><COLUMN>29</COLUMN><KEYEVENT><ID>3</ID><KIND>branch</KIND><IMPORTANCE>Full</IMPORTANCE><MESSAGE>Skip this branch, (assume '&lt;branch condition&gt;' is false)</MESSAGE></KEYEVENT></SFA><SFA><FILEPATH>n:\wpi\cs 502 os\z502 ws\</FILEPATH><FILENAME>z502.c</FILENAME><LINE>2388</LINE><COLUMN>41</COLUMN></SFA><SFA><FILEPATH>n:\wpi\cs 502 os\z502 ws\</FILEPATH><FILENAME>z502.c</FILENAME><LINE>2388</LINE><COLUMN>15</COLUMN><KEYEVENT><ID>4</ID><KIND>branch</KIND><IMPORTANCE>Full</IMPORTANCE><MESSAGE>Enter this loop, (assume 'i&lt;25+5')</MESSAGE></KEYEVENT></SFA><SFA><FILEPATH>n:\wpi\cs 502 os\z502 ws\</FILEPATH><FILENAME>z502.c</FILENAME><LINE>2389</LINE><COLUMN>29</COLUMN><KEYEVENT><ID>5</ID><KIND>branch</KIND><IMPORTANCE>Full</IMPORTANCE><MESSAGE>Skip this branch, (assume '&lt;branch condition&gt;' is false)</MESSAGE></KEYEVENT></SFA><SFA><FILEPATH>n:\wpi\cs 502 os\z502 ws\</FILEPATH><FILENAME>z502.c</FILENAME><LINE>2388</LINE><COLUMN>41</COLUMN></SFA><SFA><FILEPATH>n:\wpi\cs 502 os\z502 ws\</FILEPATH><FILENAME>z502.c</FILENAME><LINE>2388</LINE><COLUMN>15</COLUMN><KEYEVENT><ID>6</ID><KIND>branch</KIND><IMPORTANCE>Full</IMPORTANCE><MESSAGE>Continue this loop, (assume 'i&lt;25+5')</MESSAGE></KEYEVENT></SFA><SFA><FILEPATH>n:\wpi\cs 502 os\z502 ws\</FILEPATH><FILENAME>z502.c</FILENAME><LINE>2394</LINE><COLUMN>16</COLUMN><KEYEVENT><ID>7</ID><KIND>branch</KIND><IMPORTANCE>Full</IMPORTANCE><MESSAGE>Enter this branch, (assume 'ourLocalID==-1')</MESSAGE></KEYEVENT></SFA><SFA><FILEPATH>n:\wpi\cs 502 os\z502 ws\</FILEPATH><FILENAME>z502.c</FILENAME><LINE>2395</LINE><COLUMN>8</COLUMN></SFA><SFA><FILEPATH>n:\wpi\cs 502 os\z502 ws\</FILEPATH><FILENAME>z502.c</FILENAME><LINE>2396</LINE><COLUMN>23</COLUMN></SFA><SFA><FILEPATH>n:\wpi\cs 502 os\z502 ws\</FILEPATH><FILENAME>z502.c</FILENAME><LINE>2398</LINE><COLUMN>38</COLUMN><KEYEVENT><ID>8</ID><KIND>usage</KIND><IMPORTANCE>Essential</IMPORTANCE><MESSAGE>Invalid write to 'ThreadTable[-1]', (writable range is 0 to 29)</MESSAGE></KEYEVENT></SFA></PATH></DEFECT><DEFECT><SFA><FILEPATH>n:\wpi\cs 502 os\z502 ws\</FILEPATH><FILENAME>z502.c</FILENAME><LINE>2400</LINE><COLUMN>16</COLUMN></SFA><DEFECTCODE>6385</DEFECTCODE><DESCRIPTION>Reading invalid data from 'ThreadTable':  the readable size is '840' bytes, but '-28' bytes may be read.</DESCRIPTION><FUNCTION>ResumeProcessExecution</FUNCTION><DECORATED>ResumeProcessExecution</DECORATED><FUNCLINE>2383</FUNCLINE><PROBABILITY>1</PROBABILITY><RANK>4</RANK><CATEGORY><RULECATEGORY>mspft</RULECATEGORY></CATEGORY><PATH><SFA><FILEPATH>n:\wpi\cs 502 os\z502 ws\</FILEPATH><FILENAME>z502.c</FILENAME><LINE>2384</LINE><COLUMN>5</COLUMN><KEYEVENT><ID>1</ID><KIND>declaration</KIND><IMPORTANCE>Essential</IMPORTANCE><MESSAGE>'ourLocalID' is equal to -1</MESSAGE></KEYEVENT></SFA><SFA><FILEPATH>n:\wpi\cs 502 os\z502 ws\</FILEPATH><FILENAME>z502.c</FILENAME><LINE>2385</LINE><COLUMN>5</COLUMN></SFA><SFA><FILEPATH>n:\wpi\cs 502 os\z502 ws\</FILEPATH><FILENAME>z502.c</FILENAME><LINE>2387</LINE><COLUMN>8</COLUMN></SFA><SFA><FILEPATH>n:\wpi\cs 502 os\z502 ws\</FILEPATH><FILENAME>z502.c</FILENAME><LINE>2388</LINE><COLUMN>8</COLUMN></SFA><SFA><FILEPATH>n:\wpi\cs 502 os\z502 ws\</FILEPATH><FILENAME>z502.c</FILENAME><LINE>2388</LINE><COLUMN>15</COLUMN><KEYEVENT><ID>2</ID><KIND>branch</KIND><IMPORTANCE>Full</IMPORTANCE><MESSAGE>Enter this loop, (assume 'i&lt;25+5')</MESSAGE></KEYEVENT></SFA><SFA><FILEPATH>n:\wpi\cs 502 os\z502 ws\</FILEPATH><FILENAME>z502.c</FILENAME><LINE>2389</LINE><COLUMN>29</COLUMN><KEYEVENT><ID>3</ID><KIND>branch</KIND><IMPORTANCE>Full</IMPORTANCE><MESSAGE>Skip this branch, (assume '&lt;branch condition&gt;' is false)</MESSAGE></KEYEVENT></SFA><SFA><FILEPATH>n:\wpi\cs 502 os\z502 ws\</FILEPATH><FILENAME>z502.c</FILENAME><LINE>2388</LINE><COLUMN>41</COLUMN></SFA><SFA><FILEPATH>n:\wpi\cs 502 os\z502 ws\</FILEPATH><FILENAME>z502.c</FILENAME><LINE>2388</LINE><COLUMN>15</COLUMN><KEYEVENT><ID>4</ID><KIND>branch</KIND><IMPORTANCE>Full</IMPORTANCE><MESSAGE>Enter this loop, (assume 'i&lt;25+5')</MESSAGE></KEYEVENT></SFA><SFA><FILEPATH>n:\wpi\cs 502 os\z502 ws\</FILEPATH><FILENAME>z502.c</FILENAME><LINE>2389</LINE><COLUMN>29</COLUMN><KEYEVENT><ID>5</ID><KIND>branch</KIND><IMPORTANCE>Full</IMPORTANCE><MESSAGE>Skip this branch, (assume '&lt;branch condition&gt;' is false)</MESSAGE></KEYEVENT></SFA><SFA><FILEPATH>n:\wpi\cs 502 os\z502 ws\</FILEPATH><FILENAME>z502.c</FILENAME><LINE>2388</LINE><COLUMN>41</COLUMN></SFA><SFA><FILEPATH>n:\wpi\cs 502 os\z502 ws\</FILEPATH><FILENAME>z502.c</FILENAME><LINE>2388</LINE><COLUMN>15</COLUMN><KEYEVENT><ID>6</ID><KIND>branch</KIND><IMPORTANCE>Full</IMPORTANCE><MESSAGE>Continue this loop, (assume 'i&lt;25+5')</MESSAGE></KEYEVENT></SFA><SFA><FILEPATH>n:\wpi\cs 502 os\z502 ws\</FILEPATH><FILENAME>z502.c</FILENAME><LINE>2394</LINE><COLUMN>16</COLUMN><KEYEVENT><ID>7</ID><KIND>branch</KIND><IMPORTANCE>Full</IMPORTANCE><MESSAGE>Enter this branch, (assume 'ourLocalID==-1')</MESSAGE></KEYEVENT></SFA><SFA><FILEPATH>n:\wpi\cs 502 os\z502 ws\</FILEPATH><FILENAME>z502.c</FILENAME><LINE>2395</LINE><COLUMN>8</COLUMN></SFA><SFA><FILEPATH>n:\wpi\cs 502 os\z502 ws\</FILEPATH><FILENAME>z502.c</FILENAME><LINE>2396</LINE><COLUMN>23</COLUMN></SFA><SFA><FILEPATH>n:\wpi\cs 502 os\z502 ws\</FILEPATH><FILENAME>z502.c</FILENAME><LINE>2398</LINE><COLUMN>38</COLUMN></SFA><SFA><FILEPATH>n:\wpi\cs 502 os\z502 ws\</FILEPATH><FILENAME>z502.c</FILENAME><LINE>2399</LINE><COLUMN>17</COLUMN></SFA><SFA><FILEPATH>n:\wpi\cs 502 os\z502 ws\</FILEPATH><FILENAME>z502.c</FILENAME><LINE>2400</LINE><COLUMN>16</COLUMN><KEYEVENT><ID>8</ID><KIND>declaration</KIND><IMPORTANCE>Full</IMPORTANCE><MESSAGE>'ThreadTable' is an In/Out argument to 'SignalCondition' (declared on line 138)</MESSAGE></KEYEVENT></SFA><SFA><FILEPATH>n:\wpi\cs 502 os\z502 ws\</FILEPATH><FILENAME>z502.c</FILENAME><LINE>2400</LINE><COLUMN>16</COLUMN><KEYEVENT><ID>9</ID><KIND>usage</KIND><IMPORTANCE>Essential</IMPORTANCE><MESSAGE>Invalid read from 'ThreadTable[-1]', (readable range is 0 to 29)</MESSAGE></KEYEVENT></SFA></PATH></DEFECT><DEFECT><SFA><FILEPATH>n:\wpi\cs 502 os\z502 ws\</FILEPATH><FILENAME>z502.c</FILENAME><LINE>2444</LINE><COLUMN>17</COLUMN></SFA><DEFECTCODE>6385</DEFECTCODE><DESCRIPTION>Reading invalid data from 'ThreadTable':  the readable size is '840' bytes, but '-28' bytes may be read.</DESCRIPTION><FUNCTION>SuspendProcessExecution</FUNCTION><DECORATED>SuspendProcessExecution</DECORATED><FUNCLINE>2410</FUNCLINE><PROBABILITY>1</PROBABILITY><RANK>4</RANK><CATEGORY><RULECATEGORY>mspft</RULECATEGORY></CATEGORY><PATH><SFA><FILEPATH>n:\wpi\cs 502 os\z502 ws\</FILEPATH><FILENAME>z502.c</FILENAME><LINE>2411</LINE><COLUMN>5</COLUMN><KEYEVENT><ID>1</ID><KIND>declaration</KIND><IMPORTANCE>Essential</IMPORTANCE><MESSAGE>'ourLocalID' is equal to -1</MESSAGE></KEYEVENT></SFA><SFA><FILEPATH>n:\wpi\cs 502 os\z502 ws\</FILEPATH><FILENAME>z502.c</FILENAME><LINE>2412</LINE><COLUMN>5</COLUMN></SFA><SFA><FILEPATH>n:\wpi\cs 502 os\z502 ws\</FILEPATH><FILENAME>z502.c</FILENAME><LINE>2413</LINE><COLUMN>8</COLUMN></SFA><SFA><FILEPATH>n:\wpi\cs 502 os\z502 ws\</FILEPATH><FILENAME>z502.c</FILENAME><LINE>2414</LINE><COLUMN>7</COLUMN></SFA><SFA><FILEPATH>n:\wpi\cs 502 os\z502 ws\</FILEPATH><FILENAME>z502.c</FILENAME><LINE>2419</LINE><COLUMN>13</COLUMN><KEYEVENT><ID>2</ID><KIND>branch</KIND><IMPORTANCE>Full</IMPORTANCE><MESSAGE>Skip this branch, (assume 'Context==(((void *)0))' is false)</MESSAGE></KEYEVENT></SFA><SFA><FILEPATH>n:\wpi\cs 502 os\z502 ws\</FILEPATH><FILENAME>z502.c</FILENAME><LINE>2432</LINE><COLUMN>8</COLUMN></SFA><SFA><FILEPATH>n:\wpi\cs 502 os\z502 ws\</FILEPATH><FILENAME>z502.c</FILENAME><LINE>2432</LINE><COLUMN>15</COLUMN><KEYEVENT><ID>3</ID><KIND>branch</KIND><IMPORTANCE>Full</IMPORTANCE><MESSAGE>Enter this loop, (assume 'i&lt;25+5')</MESSAGE></KEYEVENT></SFA><SFA><FILEPATH>n:\wpi\cs 502 os\z502 ws\</FILEPATH><FILENAME>z502.c</FILENAME><LINE>2433</LINE><COLUMN>29</COLUMN><KEYEVENT><ID>4</ID><KIND>branch</KIND><IMPORTANCE>Full</IMPORTANCE><MESSAGE>Skip this branch, (assume '&lt;branch condition&gt;' is false)</MESSAGE></KEYEVENT></SFA><SFA><FILEPATH>n:\wpi\cs 502 os\z502 ws\</FILEPATH><FILENAME>z502.c</FILENAME><LINE>2432</LINE><COLUMN>41</COLUMN></SFA><SFA><FILEPATH>n:\wpi\cs 502 os\z502 ws\</FILEPATH><FILENAME>z502.c</FILENAME><LINE>2432</LINE><COLUMN>15</COLUMN><KEYEVENT><ID>5</ID><KIND>branch</KIND><IMPORTANCE>Full</IMPORTANCE><MESSAGE>Enter this loop, (assume 'i&lt;25+5')</MESSAGE></KEYEVENT></SFA><SFA><FILEPATH>n:\wpi\cs 502 os\z502 ws\</FILEPATH><FILENAME>z502.c</FILENAME><LINE>2433</LINE><COLUMN>29</COLUMN><KEYEVENT><ID>6</ID><KIND>branch</KIND><IMPORTANCE>Full</IMPORTANCE><MESSAGE>Skip this branch, (assume '&lt;branch condition&gt;' is false)</MESSAGE></KEYEVENT></SFA><SFA><FILEPATH>n:\wpi\cs 502 os\z502 ws\</FILEPATH><FILENAME>z502.c</FILENAME><LINE>2432</LINE><COLUMN>41</COLUMN></SFA><SFA><FILEPATH>n:\wpi\cs 502 os\z502 ws\</FILEPATH><FILENAME>z502.c</FILENAME><LINE>2432</LINE><COLUMN>15</COLUMN><KEYEVENT><ID>7</ID><KIND>branch</KIND><IMPORTANCE>Full</IMPORTANCE><MESSAGE>Continue this loop, (assume 'i&lt;25+5')</MESSAGE></KEYEVENT></SFA><SFA><FILEPATH>n:\wpi\cs 502 os\z502 ws\</FILEPATH><FILENAME>z502.c</FILENAME><LINE>2438</LINE><COLUMN>16</COLUMN><KEYEVENT><ID>8</ID><KIND>branch</KIND><IMPORTANCE>Full</IMPORTANCE><MESSAGE>Enter this branch, (assume 'ourLocalID==-1')</MESSAGE></KEYEVENT></SFA><SFA><FILEPATH>n:\wpi\cs 502 os\z502 ws\</FILEPATH><FILENAME>z502.c</FILENAME><LINE>2439</LINE><COLUMN>8</COLUMN></SFA><SFA><FILEPATH>n:\wpi\cs 502 os\z502 ws\</FILEPATH><FILENAME>z502.c</FILENAME><LINE>2440</LINE><COLUMN>23</COLUMN></SFA><SFA><FILEPATH>n:\wpi\cs 502 os\z502 ws\</FILEPATH><FILENAME>z502.c</FILENAME><LINE>2442</LINE><COLUMN>17</COLUMN></SFA><SFA><FILEPATH>n:\wpi\cs 502 os\z502 ws\</FILEPATH><FILENAME>z502.c</FILENAME><LINE>2444</LINE><COLUMN>17</COLUMN><KEYEVENT><ID>9</ID><KIND>declaration</KIND><IMPORTANCE>Full</IMPORTANCE><MESSAGE>'ThreadTable' is an In/Out argument to 'WaitForCondition' (declared on line 142)</MESSAGE></KEYEVENT></SFA><SFA><FILEPATH>n:\wpi\cs 502 os\z502 ws\</FILEPATH><FILENAME>z502.c</FILENAME><LINE>2444</LINE><COLUMN>17</COLUMN><KEYEVENT><ID>10</ID><KIND>usage</KIND><IMPORTANCE>Essential</IMPORTANCE><MESSAGE>Invalid read from 'ThreadTable[-1]', (readable range is 0 to 29)</MESSAGE></KEYEVENT></SFA></PATH></DEFECT><DEFECT><SFA><FILEPATH>n:\wpi\cs 502 os\z502 ws\</FILEPATH><FILENAME>z502.c</FILENAME><LINE>2542</LINE><COLUMN>17</COLUMN></SFA><DEFECTCODE>6001</DEFECTCODE><DESCRIPTION>Using uninitialized memory 'ReturnValue'.</DESCRIPTION><FUNCTION>ChangeThreadPriority</FUNCTION><DECORATED>ChangeThreadPriority</DECORATED><FUNCLINE>2531</FUNCLINE><PROBABILITY>1</PROBABILITY><RANK>3</RANK><CATEGORY><RULECATEGORY>mspft</RULECATEGORY></CATEGORY><PATH><SFA><FILEPATH>n:\wpi\cs 502 os\z502 ws\</FILEPATH><FILENAME>z502.c</FILENAME><LINE>2533</LINE><COLUMN>7</COLUMN><KEYEVENT><ID>1</ID><KIND>declaration</KIND><IMPORTANCE>Essential</IMPORTANCE><MESSAGE>'ReturnValue' is not initialized</MESSAGE></KEYEVENT></SFA><SFA><FILEPATH>n:\wpi\cs 502 os\z502 ws\</FILEPATH><FILENAME>z502.c</FILENAME><LINE>2534</LINE><COLUMN>8</COLUMN></SFA><SFA><FILEPATH>n:\wpi\cs 502 os\z502 ws\</FILEPATH><FILENAME>z502.c</FILENAME><LINE>2535</LINE><COLUMN>12</COLUMN></SFA><SFA><FILEPATH>n:\wpi\cs 502 os\z502 ws\</FILEPATH><FILENAME>z502.c</FILENAME><LINE>2536</LINE><COLUMN>23</COLUMN><KEYEVENT><ID>2</ID><KIND>branch</KIND><IMPORTANCE>Full</IMPORTANCE><MESSAGE>Skip this branch, (assume 'PriorityDirection==5' is false)</MESSAGE></KEYEVENT></SFA><SFA><FILEPATH>n:\wpi\cs 502 os\z502 ws\</FILEPATH><FILENAME>z502.c</FILENAME><LINE>2539</LINE><COLUMN>23</COLUMN><KEYEVENT><ID>3</ID><KIND>branch</KIND><IMPORTANCE>Full</IMPORTANCE><MESSAGE>Skip this branch, (assume 'PriorityDirection==-5' is false)</MESSAGE></KEYEVENT></SFA><SFA><FILEPATH>n:\wpi\cs 502 os\z502 ws\</FILEPATH><FILENAME>z502.c</FILENAME><LINE>2542</LINE><COLUMN>17</COLUMN><KEYEVENT><ID>4</ID><KIND>usage</KIND><IMPORTANCE>Essential</IMPORTANCE><MESSAGE>'ReturnValue' is used, but may not have been initialized</MESSAGE></KEYEVENT></SFA></PATH></DEFECT><DEFECT><SFA><FILEPATH>n:\wpi\cs 502 os\z502 ws\</FILEPATH><FILENAME>z502.c</FILENAME><LINE>2704</LINE><COLUMN>1</COLUMN></SFA><DEFECTCODE>26135</DEFECTCODE><DESCRIPTION>Missing annotation _Acquires_lock_(MemoryMutex) at function 'GetTryLock'.</DESCRIPTION><FUNCTION>GetTryLock</FUNCTION><DECORATED>GetTryLock</DECORATED><FUNCLINE>2666</FUNCLINE><PATH><SFA><FILEPATH>n:\wpi\cs 502 os\z502 ws\</FILEPATH><FILENAME>z502.c</FILENAME><LINE>2666</LINE><COLUMN>4</COLUMN></SFA><SFA><FILEPATH>n:\wpi\cs 502 os\z502 ws\</FILEPATH><FILENAME>z502.c</FILENAME><LINE>2667</LINE><COLUMN>5</COLUMN></SFA><SFA><FILEPATH>n:\wpi\cs 502 os\z502 ws\</FILEPATH><FILENAME>z502.c</FILENAME><LINE>2668</LINE><COLUMN>5</COLUMN></SFA><SFA><FILEPATH>n:\wpi\cs 502 os\z502 ws\</FILEPATH><FILENAME>z502.c</FILENAME><LINE>2670</LINE><COLUMN>8</COLUMN></SFA><SFA><FILEPATH>n:\wpi\cs 502 os\z502 ws\</FILEPATH><FILENAME>z502.c</FILENAME><LINE>2673</LINE><COLUMN>15</COLUMN></SFA><SFA><FILEPATH>n:\wpi\cs 502 os\z502 ws\</FILEPATH><FILENAME>z502.c</FILENAME><LINE>2675</LINE><COLUMN>13</COLUMN></SFA><SFA><FILEPATH>n:\wpi\cs 502 os\z502 ws\</FILEPATH><FILENAME>z502.c</FILENAME><LINE>2676</LINE><COLUMN>39</COLUMN></SFA><SFA><FILEPATH>n:\wpi\cs 502 os\z502 ws\</FILEPATH><FILENAME>z502.c</FILENAME><LINE>2678</LINE><COLUMN>16</COLUMN></SFA><SFA><FILEPATH>n:\wpi\cs 502 os\z502 ws\</FILEPATH><FILENAME>z502.c</FILENAME><LINE>2683</LINE><COLUMN>16</COLUMN></SFA><SFA><FILEPATH>n:\wpi\cs 502 os\z502 ws\</FILEPATH><FILENAME>z502.c</FILENAME><LINE>2685</LINE><COLUMN>5</COLUMN></SFA><SFA><FILEPATH>n:\wpi\cs 502 os\z502 ws\</FILEPATH><FILENAME>z502.c</FILENAME><LINE>2686</LINE><COLUMN>14</COLUMN></SFA><SFA><FILEPATH>n:\wpi\cs 502 os\z502 ws\</FILEPATH><FILENAME>z502.c</FILENAME><LINE>2703</LINE><COLUMN>15</COLUMN></SFA><SFA><FILEPATH>n:\wpi\cs 502 os\z502 ws\</FILEPATH><FILENAME>z502.c</FILENAME><LINE>2704</LINE><COLUMN>1</COLUMN></SFA></PATH></DEFECT><DEFECT><SFA><FILEPATH>n:\wpi\cs 502 os\z502 ws\</FILEPATH><FILENAME>z502.c</FILENAME><LINE>2756</LINE><COLUMN>1</COLUMN></SFA><DEFECTCODE>26135</DEFECTCODE><DESCRIPTION>Missing annotation _Acquires_lock_(MemoryMutex) at function 'GetLock'.</DESCRIPTION><FUNCTION>GetLock</FUNCTION><DECORATED>GetLock</DECORATED><FUNCLINE>2716</FUNCLINE><PATH><SFA><FILEPATH>n:\wpi\cs 502 os\z502 ws\</FILEPATH><FILENAME>z502.c</FILENAME><LINE>2716</LINE><COLUMN>4</COLUMN></SFA><SFA><FILEPATH>n:\wpi\cs 502 os\z502 ws\</FILEPATH><FILENAME>z502.c</FILENAME><LINE>2717</LINE><COLUMN>7</COLUMN></SFA><SFA><FILEPATH>n:\wpi\cs 502 os\z502 ws\</FILEPATH><FILENAME>z502.c</FILENAME><LINE>2718</LINE><COLUMN>5</COLUMN></SFA><SFA><FILEPATH>n:\wpi\cs 502 os\z502 ws\</FILEPATH><FILENAME>z502.c</FILENAME><LINE>2720</LINE><COLUMN>8</COLUMN></SFA><SFA><FILEPATH>n:\wpi\cs 502 os\z502 ws\</FILEPATH><FILENAME>z502.c</FILENAME><LINE>2722</LINE><COLUMN>15</COLUMN></SFA><SFA><FILEPATH>n:\wpi\cs 502 os\z502 ws\</FILEPATH><FILENAME>z502.c</FILENAME><LINE>2724</LINE><COLUMN>33</COLUMN></SFA><SFA><FILEPATH>n:\wpi\cs 502 os\z502 ws\</FILEPATH><FILENAME>z502.c</FILENAME><LINE>2725</LINE><COLUMN>5</COLUMN></SFA><SFA><FILEPATH>n:\wpi\cs 502 os\z502 ws\</FILEPATH><FILENAME>z502.c</FILENAME><LINE>2730</LINE><COLUMN>5</COLUMN></SFA><SFA><FILEPATH>n:\wpi\cs 502 os\z502 ws\</FILEPATH><FILENAME>z502.c</FILENAME><LINE>2731</LINE><COLUMN>14</COLUMN></SFA><SFA><FILEPATH>n:\wpi\cs 502 os\z502 ws\</FILEPATH><FILENAME>z502.c</FILENAME><LINE>2755</LINE><COLUMN>15</COLUMN></SFA><SFA><FILEPATH>n:\wpi\cs 502 os\z502 ws\</FILEPATH><FILENAME>z502.c</FILENAME><LINE>2756</LINE><COLUMN>1</COLUMN></SFA></PATH></DEFECT><DEFECT><SFA><FILEPATH>n:\wpi\cs 502 os\z502 ws\</FILEPATH><FILENAME>z502.c</FILENAME><LINE>2796</LINE><COLUMN>1</COLUMN></SFA><DEFECTCODE>26135</DEFECTCODE><DESCRIPTION>Missing annotation _Releases_lock_(MemoryMutex) at function 'ReleaseLock'.</DESCRIPTION><FUNCTION>ReleaseLock</FUNCTION><DECORATED>ReleaseLock</DECORATED><FUNCLINE>2765</FUNCLINE><PATH><SFA><FILEPATH>n:\wpi\cs 502 os\z502 ws\</FILEPATH><FILENAME>z502.c</FILENAME><LINE>2765</LINE><COLUMN>4</COLUMN></SFA><SFA><FILEPATH>n:\wpi\cs 502 os\z502 ws\</FILEPATH><FILENAME>z502.c</FILENAME><LINE>2766</LINE><COLUMN>5</COLUMN></SFA><SFA><FILEPATH>n:\wpi\cs 502 os\z502 ws\</FILEPATH><FILENAME>z502.c</FILENAME><LINE>2767</LINE><COLUMN>5</COLUMN></SFA><SFA><FILEPATH>n:\wpi\cs 502 os\z502 ws\</FILEPATH><FILENAME>z502.c</FILENAME><LINE>2769</LINE><COLUMN>8</COLUMN></SFA><SFA><FILEPATH>n:\wpi\cs 502 os\z502 ws\</FILEPATH><FILENAME>z502.c</FILENAME><LINE>2771</LINE><COLUMN>15</COLUMN></SFA><SFA><FILEPATH>n:\wpi\cs 502 os\z502 ws\</FILEPATH><FILENAME>z502.c</FILENAME><LINE>2774</LINE><COLUMN>26</COLUMN></SFA><SFA><FILEPATH>n:\wpi\cs 502 os\z502 ws\</FILEPATH><FILENAME>z502.c</FILENAME><LINE>2776</LINE><COLUMN>5</COLUMN></SFA><SFA><FILEPATH>n:\wpi\cs 502 os\z502 ws\</FILEPATH><FILENAME>z502.c</FILENAME><LINE>2795</LINE><COLUMN>15</COLUMN></SFA><SFA><FILEPATH>n:\wpi\cs 502 os\z502 ws\</FILEPATH><FILENAME>z502.c</FILENAME><LINE>2796</LINE><COLUMN>1</COLUMN></SFA></PATH></DEFECT><DEFECT><SFA><FILEPATH>n:\wpi\cs 502 os\z502 ws\</FILEPATH><FILENAME>z502.c</FILENAME><LINE>3027</LINE><COLUMN>9</COLUMN></SFA><DEFECTCODE>6340</DEFECTCODE><DESCRIPTION>Mismatch on sign: 'unsigned int' passed as _Param_(7) when some signed type is required in call to 'sprintf'.</DESCRIPTION><FUNCTION>PrintLockDebug</FUNCTION><DECORATED>PrintLockDebug</DECORATED><FUNCLINE>2824</FUNCLINE><PATH/></DEFECT><DEFECT><SFA><FILEPATH>n:\wpi\cs 502 os\z502 ws\</FILEPATH><FILENAME>z502.c</FILENAME><LINE>3085</LINE><COLUMN>8</COLUMN></SFA><DEFECTCODE>6340</DEFECTCODE><DESCRIPTION>Mismatch on sign: 'unsigned int' passed as _Param_(2) when some signed type is required in call to 'printf'.</DESCRIPTION><FUNCTION>CreateCondition</FUNCTION><DECORATED>CreateCondition</DECORATED><FUNCLINE>3053</FUNCLINE><PATH/></DEFECT><DEFECT><SFA><FILEPATH>n:\wpi\cs 502 os\z502 ws\</FILEPATH><FILENAME>z502.c</FILENAME><LINE>3100</LINE><COLUMN>8</COLUMN></SFA><DEFECTCODE>6340</DEFECTCODE><DESCRIPTION>Mismatch on sign: 'unsigned int' passed as _Param_(2) when some signed type is required in call to 'printf'.</DESCRIPTION><FUNCTION>WaitForCondition</FUNCTION><DECORATED>WaitForCondition</DECORATED><FUNCLINE>3095</FUNCLINE><PATH/></DEFECT><DEFECT><SFA><FILEPATH>n:\wpi\cs 502 os\z502 ws\</FILEPATH><FILENAME>z502.c</FILENAME><LINE>3100</LINE><COLUMN>8</COLUMN></SFA><DEFECTCODE>6340</DEFECTCODE><DESCRIPTION>Mismatch on sign: 'unsigned int' passed as _Param_(3) when some signed type is required in call to 'printf'.</DESCRIPTION><FUNCTION>WaitForCondition</FUNCTION><DECORATED>WaitForCondition</DECORATED><FUNCLINE>3095</FUNCLINE><PATH/></DEFECT><DEFECT><SFA><FILEPATH>n:\wpi\cs 502 os\z502 ws\</FILEPATH><FILENAME>z502.c</FILENAME><LINE>3134</LINE><COLUMN>8</COLUMN></SFA><DEFECTCODE>6340</DEFECTCODE><DESCRIPTION>Mismatch on sign: 'unsigned int' passed as _Param_(2) when some signed type is required in call to 'printf'.</DESCRIPTION><FUNCTION>WaitForCondition</FUNCTION><DECORATED>WaitForCondition</DECORATED><FUNCLINE>3095</FUNCLINE><PATH/></DEFECT><DEFECT><SFA><FILEPATH>n:\wpi\cs 502 os\z502 ws\</FILEPATH><FILENAME>z502.c</FILENAME><LINE>3134</LINE><COLUMN>8</COLUMN></SFA><DEFECTCODE>6340</DEFECTCODE><DESCRIPTION>Mismatch on sign: 'unsigned int' passed as _Param_(3) when some signed type is required in call to 'printf'.</DESCRIPTION><FUNCTION>WaitForCondition</FUNCTION><DECORATED>WaitForCondition</DECORATED><FUNCLINE>3095</FUNCLINE><PATH/></DEFECT><DEFECT><SFA><FILEPATH>n:\wpi\cs 502 os\z502 ws\</FILEPATH><FILENAME>z502.c</FILENAME><LINE>3156</LINE><COLUMN>8</COLUMN></SFA><DEFECTCODE>6340</DEFECTCODE><DESCRIPTION>Mismatch on sign: 'unsigned int' passed as _Param_(2) when some signed type is required in call to 'printf'.</DESCRIPTION><FUNCTION>SignalCondition</FUNCTION><DECORATED>SignalCondition</DECORATED><FUNCLINE>3146</FUNCLINE><PATH/></DEFECT><DEFECT><SFA><FILEPATH>n:\wpi\cs 502 os\z502 ws\</FILEPATH><FILENAME>z502.c</FILENAME><LINE>3156</LINE><COLUMN>8</COLUMN></SFA><DEFECTCODE>6340</DEFECTCODE><DESCRIPTION>Mismatch on sign: 'unsigned int' passed as _Param_(3) when some signed type is required in call to 'printf'.</DESCRIPTION><FUNCTION>SignalCondition</FUNCTION><DECORATED>SignalCondition</DECORATED><FUNCLINE>3146</FUNCLINE><PATH/></DEFECT><DEFECT><SFA><FILEPATH>n:\wpi\cs 502 os\z502 ws\</FILEPATH><FILENAME>z502.c</FILENAME><LINE>3189</LINE><COLUMN>8</COLUMN></SFA><DEFECTCODE>6340</DEFECTCODE><DESCRIPTION>Mismatch on sign: 'unsigned int' passed as _Param_(2) when some signed type is required in call to 'printf'.</DESCRIPTION><FUNCTION>SignalCondition</FUNCTION><DECORATED>SignalCondition</DECORATED><FUNCLINE>3146</FUNCLINE><PATH/></DEFECT><DEFECT><SFA><FILEPATH>n:\wpi\cs 502 os\z502 ws\</FILEPATH><FILENAME>z502.c</FILENAME><LINE>3189</LINE><COLUMN>8</COLUMN></SFA><DEFECTCODE>6340</DEFECTCODE><DESCRIPTION>Mismatch on sign: 'unsigned int' passed as _Param_(3) when some signed type is required in call to 'printf'.</DESCRIPTION><FUNCTION>SignalCondition</FUNCTION><DECORATED>SignalCondition</DECORATED><FUNCLINE>3146</FUNCLINE><PATH/></DEFECT></DEFECTS>